Workbook

Sheet SOP
A2: STANDAR OPERASIONAL PROSEDUR
A4: JUDUL | B4: SOP Project Workflow One Spirit Asia
A5: DEPARTEMEN | B5: ALL DEPT
A6: NO DOKUMEN | B6: SOP.OSA.08.IX.2025
A7: TANGGAL PEMBUATAN | B7: 45929
A8: TANGGAL PERUBAHAN | D8: Rev:
A10: 1. Tujuan | B10: Menetapkan alur kerja standar project dari tahap inquiry sampai closing agar seluruh proses tercatat, terdokumentasi, dan terkendali dengan baik sehingga meminimalisir kesalahan, meningkatkan efisiensi, serta memastikan kualitas layanan kepada klien.
A11: 2. Ruang Lingkup | B11: SOP ini berlaku untuk seluruh project event yang ditangani One Spirit Asia, mencakup divisi: > Sales & Marketing > Program & Project > Finance & Administration > Production & Technical > Documentation
A12: 3. Definisi | B12: > Inquiry: Permintaan awal atau ketertarikan klien terhadap layanan event. > Workflow: Alur kerja standar yang harus diikuti dari awal hingga akhir project. > Milestone: Tahapan penting yang menjadi penanda progres project.
A13: 4. Pihak Bertanggung Jawab | B13: > Sales & Marketing (SM) → menerima inquiry, input data klien, koordinasi awal. > Project Manager (PM) → memastikan workflow dijalankan sesuai SOP. > Finance & Admin (FA) → mengelola anggaran, invoice, pembayaran. > Program/Creative → membuat konsep & proposal. > Production/Technical → memastikan kebutuhan teknis event. > Documentation → mengelola hasil dokumentasi (foto, video, teaser).
A14: 5. Prosedur Pelaksanaan | B14: A. Inquiry & MOM > Sales menerima inquiry klien melalui kanal resmi (email, WhatsApp, website, referral). > Sales mengisi kolom Inquiry pada Project Workflow (tanggal, nama klien, PIC, kebutuhan awal). > Sales membuat Minutes of Meeting (MOM) jika ada meeting awal, lalu upload ke folder project. B. Customer Detail > Data lengkap klien diisi di kolom Customer Detail (nama project, kategori, CP, email, nomor HP). > Sales wajib memastikan data ini lengkap sebelum masuk tahap program. C. Program Detail > Program/Creative membuat konsep & proposal sesuai kebutuhan klien. > PM mengisi kategori event, program, venue, tanggal mulai & selesai. > Draft proposal dilampirkan di folder project, link dicatat di kolom workflow. D. Progress Detail > Proposal yang sudah jadi dikirim ke klien → status dicatat (Quotation Sent). > Nomor quotation, tanggal, dan status (Pending, Won, Lost) wajib diisi. > Jika deal → upload file kontrak / signed file ke folder project, update status “Signed”. > Jika batal → isi alasan pembatalan. E. Instrument > PM bersama tim checklist kebutuhan teknis (venue, catering, stage, multimedia, dll). > Status kesiapan dicatat di kolom Instrument. F. Payment Detail > Finance mengisi estimasi budget di kolom Budget (Rp). > Finance membuat jadwal pembayaran (DP, termin, pelunasan). > Status invoice dan pembayaran wajib diupdate secara real-time. > Jika ada keterlambatan, Finance follow up & catat di kolom Note. G. Dokumentasi > Tim dokumentasi wajib menyimpan semua hasil dokumentasi di folder drive. > Link foto, video, teaser, dan media sosial (IG/YouTube) dicatat di workflow. H. Closing Project Project dianggap SELESAI jika: > Semua milestone tercapai. > Seluruh pembayaran lunas. > Dokumentasi lengkap & diarsipkan. > Laporan P&L project sudah selesai. *Workflow di-lock oleh PM dan hanya bisa dibuka kembali oleh Finance/Admin jika ada audit.
A15: 6. Kontrol & Evaluasi | B15: > PM wajib melakukan review mingguan atas semua project di workflow. > Laporan bulanan diserahkan ke Managing Director. > Evaluasi project dilakukan 1 minggu setelah event untuk catatan perbaikan.
A16: 7. Konsekuensi Ketidakpatuhan | B16: a. Progress di Luar Workflow > Jika karyawan mengerjakan project tetapi tidak tercantum dalam Project Workflow, maka progress tersebut dianggap sebagai project pribadi, bukan bagian dari project perusahaan dan dianggap menyalahi aturan yang berlaku. > Segala bentuk progress yang tidak tercatat di Project Workflow tidak diakui sebagai tanggung jawab perusahaan. b. Kelengkapan Data Workflow & Insentif > Jika Project Workflow tidak dilengkapi atau tidak diisi sesuai SOP, maka project dianggap belum memenuhi standar administrasi. > Akibatnya, insentif project tidak dapat diklaim atau dicairkan sampai data dinyatakan lengkap.
A17: 8. Keamanan Data & Privasi | B17: a. Kerahasiaan Data > Seluruh data yang tercantum dalam Project Workflow (customer detail, budget, quotation, invoice, dokumentasi, dll.) merupakan aset perusahaan dan bersifat rahasia. > Data hanya boleh diakses dan digunakan untuk kepentingan pekerjaan sesuai dengan SOP. b. Larangan Penyalahgunaan > Dilarang keras mengambil, menyalin, membagikan, atau menggunakan data klien maupun data perusahaan yang tercantum dalam Project Workflow untuk kepentingan pribadi atau pihak luar. > Pelanggaran atas poin ini akan dianggap sebagai tindak penyalahgunaan aset perusahaan dan dapat dikenakan tindakan disiplin sesuai peraturan yang berlaku. c. Akses Terbatas > Akses ke Project Workflow hanya diberikan kepada karyawan sesuai kewenangan dan tanggung jawabnya. > Setiap karyawan wajib menjaga akun, password, serta akses login agar tidak digunakan oleh pihak yang tidak berhak.

Sheet Dashboard
B3: Simple Dashboard
B7: Potential Revenue | F7: Revenue Confirmed | L7: =Helper!J44 -> Quotation Status | P7: =Helper!J11 -> Program Status | T7: =Helper!J23 -> Payment Status | X7: =Helper!M38 -> Customer Category
L8: =Helper!K45 -> 142 | N8: Cancel | P8: =Helper!K12 -> 142 | R8: =Helper!J12 -> Cancel | T8: =Helper!K24 -> 1 | V8: Invoice Sent | X8: =Helper!N40 -> 4 | Z8: =Helper!M40 -> Campus | AB8: =Helper!N43 -> 17 | AD8: =Helper!M43 -> Other
F9: Target 2025 | G9: 9200000000 | H9: =F10/G9*100% -> 1.1492938
B10: =Helper!L71 -> 31515619883 | F10: =Helper!L70 -> 10573503222 | J10: =Helper!E20 -> 0.3355004 | N10: Our Client Cancel | R10: Program Cancel | V10: Invoice in Progress
L12: =IFERROR(__xludf.DUMMYFUNCTION("IFERROR(SPARKLINE(L13,{""charttype"",""bar"";""max"",1;""min"",0;""color1"",""#ef0101""}))"),"") | P12: =IFERROR(__xludf.DUMMYFUNCTION("IFERROR(SPARKLINE(P13,{""charttype"",""bar"";""max"",1;""min"",0;""color1"",""#ef0101""}))"),"") | T12: =IFERROR(__xludf.DUMMYFUNCTION("IFERROR(SPARKLINE(T13,{""charttype"",""bar"";""max"",1;""min"",0;""color1"",""#ffe5ca""}))"),"") | X12: =IFERROR(__xludf.DUMMYFUNCTION("IFERROR(SPARKLINE(X13,{""charttype"",""bar"";""max"",1;""min"",0;""color1"",""#42bdff""}))"),"") | AB12: =IFERROR(__xludf.DUMMYFUNCTION("IFERROR(SPARKLINE(AB13,{""charttype"",""bar"";""max"",1;""min"",0;""color1"",""#42bdff""}))"),"")
L13: =L8/N13 -> 0.53787879 | N13: =B21 -> 264 | P13: =P8/R13 -> 0.53787879 | R13: =B21 -> 264 | T13: =T8/V13 -> 0.0081967213 | V13: =F21 -> 122 | X13: =X8/Z13 -> 0.015151515 | Z13: =B21 -> 264 | AB13: =AB8/AD13 -> 0.064393939 | AD13: =B21 -> 264
L14: 0 | N14: Feedback | P14: =Helper!K13 -> 122 | R14: =Helper!J13 -> Confirm | T14: =Helper!K25 -> 12 | V14: =Helper!J25 -> Out Standing | X14: =Helper!N41 -> 200 | Z14: =Helper!M41 -> Corporate | AB14: =Helper!N44 -> 4 | AD14: =Helper!M44 -> Student
R16: Program Confirm | V16: Payment in progress
F17: 2023 | G17: 2024 | H17: 2025
F18: 7751804687 | G18: 6146278045 | H18: =F10-G18 -> 4427225177 | I18: =F10-F18 -> 2821698535 | L18: =IFERROR(__xludf.DUMMYFUNCTION("IFERROR(SPARKLINE(L19,{""charttype"",""bar"";""max"",1;""min"",0;""color1"",""#ffe5ca""}))"),"") | P18: =IFERROR(__xludf.DUMMYFUNCTION("IFERROR(SPARKLINE(P19,{""charttype"",""bar"";""max"",1;""min"",0;""color1"",""#b6d7a8""}))"),"") | T18: =IFERROR(__xludf.DUMMYFUNCTION("IFERROR(SPARKLINE(T19,{""charttype"",""bar"";""max"",1;""min"",0;""color1"",""#f9cb9c""}))"),"") | X18: =IFERROR(__xludf.DUMMYFUNCTION("IFERROR(SPARKLINE(X19,{""charttype"",""bar"";""max"",1;""min"",0;""color1"",""#ea9999""}))"),"") | AB18: =IFERROR(__xludf.DUMMYFUNCTION("IFERROR(SPARKLINE(AB19,{""charttype"",""bar"";""max"",1;""min"",0;""color1"",""#ea9999""}))"),"")
B19: Total Inquiry | F19: Total Project Deal | J19: =Helper!E21 -> 0.46212121 | L19: =L14/N19 -> 0 | N19: =B21 -> 264 | P19: =P14/R19 -> 0.46212121 | R19: =B21 -> 264 | T19: =T14/V19 -> 0.098360656 | V19: =F21 -> 122 | X19: =X14/Z19 -> 0.75757576 | Z19: =B21 -> 264 | AB19: =AB14/AD19 -> 0.015151515 | AD19: =B21 -> 264
L20: 0 | N20: In Progress | P20: =Helper!K14 -> 264 | R20: Sent | T20: =Helper!K26 -> 103 | V20: =Helper!J26 -> Paid | X20: =Helper!N42 -> 37 | Z20: =Helper!M42 -> Goverment
B21: =Helper!K47 -> 264 | F21: =Helper!K70 -> 122
V22: Project Already Paid
L24: =IFERROR(__xludf.DUMMYFUNCTION("IFERROR(SPARKLINE(L25,{""charttype"",""bar"";""max"",1;""min"",0;""color1"",""#f9cb9c""}))"),"") | P24: =IFERROR(__xludf.DUMMYFUNCTION("IFERROR(SPARKLINE(P25,{""charttype"",""bar"";""max"",1;""min"",0;""color1"",""#f9cb9c""}))"),"") | T24: =IFERROR(__xludf.DUMMYFUNCTION("IFERROR(SPARKLINE(T25,{""charttype"",""bar"";""max"",1;""min"",0;""color1"",""#b6d7a8""}))"),"") | X24: =IFERROR(__xludf.DUMMYFUNCTION("IFERROR(SPARKLINE(X25,{""charttype"",""bar"";""max"",1;""min"",0;""color1"",""#f89f35""}))"),"")
L25: =L20/N25 -> 0 | N25: =B21 -> 264 | P25: =P20/R25 -> 1 | R25: =B21 -> 264 | T25: =T20/V25 -> 0.8442623 | V25: =F21 -> 122 | X25: =X20/Z25 -> 0.14015152 | Z25: =B21 -> 264 | AB25: =IFERROR(__xludf.DUMMYFUNCTION("IFERROR(SPARKLINE(AB26,{""charttype"",""bar"";""max"",1;""min"",0;""color1"",""#f89f35""}))"),"")
B26: Number of Project per Programer | L26: =Helper!K47 -> 264 | N26: Sent | P26: 0 | R26: In Progress
N28: Quotation Sent | R28: Program in Progress
L30: =IFERROR(__xludf.DUMMYFUNCTION("IFERROR(SPARKLINE(L31,{""charttype"",""bar"";""max"",1;""min"",0;""color1"",""#d7f1cc""}))"),"") | P30: =IFERROR(__xludf.DUMMYFUNCTION("IFERROR(SPARKLINE(P31,{""charttype"",""bar"";""max"",1;""min"",0;""color1"",""#ffe5ca""}))"),"")
L31: =L26/N31 -> 1 | N31: =B21 -> 264 | P31: =P26/R31 -> 0 | R31: =B21 -> 264
L32: =Helper!K46 -> 122 | N32: Sign & Deal | P32: 0
N34: Our Client Confirm & Sign | R34: Program have not started
L36: =IFERROR(__xludf.DUMMYFUNCTION("IFERROR(SPARKLINE(L37,{""charttype"",""bar"";""max"",1;""min"",0;""color1"",""#b6d7a8""}))"),"") | P36: =IFERROR(__xludf.DUMMYFUNCTION("IFERROR(SPARKLINE(P37,{""charttype"",""bar"";""max"",1;""min"",0;""color1"",""#ea9999""}))"),"")
L37: =L32/N37 -> 0.46212121 | N37: =B21 -> 264 | P37: =P32/R37 -> 0 | R37: =B21 -> 264
K57: Highest Budget | L57: =Helper!N4 -> 10976511799 | Q57: Tasks vs. Completion Dates
Q60: =Helper!V3 -> P073 | S60: =Helper!T3 -> June-2025
Q62: =Helper!V4 -> P175 | S62: =Helper!T5 -> 46042
L63: =Helper!M3 -> Direct
Q64: =Helper!V5 -> P221 | S64: =Helper!T7 -> 46019
K66: Lowest Budget | L66: =Helper!N8 -> 132043800 | Q66: =Helper!V6 -> P244 | S66: =Helper!T9 -> 46014
Q68: =Helper!V7 -> P247 | S68: =Helper!T11 -> 46009
Q70: =Helper!V8 -> P248 | S70: =Helper!T13 -> 46005
L72: Web | Q72: =Helper!V9 -> P258 | S72: =Helper!T15 -> 46003
Q74: =Helper!V10 -> P253 | S74: =Helper!T17 -> 46000
K75: Average Budget
Q76: =Helper!V11 -> P245 | S76: =Helper!T19 -> 45996
Q78: =Helper!V12 -> P256 | S78: =Helper!T21 -> 45994
Q80: =Helper!V14 -> P249 | S80: =Helper!T23 -> 45992
Q82: =Helper!V16 -> P234 | S82: =Helper!T25 -> 45990
Q84: =Helper!V18 -> P224 | S84: =Helper!T27 -> 45988

Sheet Workflow
B1: Project Workflow One Spirit 2025 | W1: QT0025/JIP/I/2025
B2: INQUERY & MOM | I2: CUSTOMER DETAIL | N2: PROGRAM DETAIL | U2: PROGRESS DETAIL | AB2: INSTRUMENT | AI2: PAYMENT DETAIL | AO2: Dokumentasi
B3: A. Inquiry & MOM -Sales menerima inquiry klien melalui kanal resmi (email, WhatsApp, website, referral). -Sales mengisi kolom Inquiry pada Project Workflow (tanggal, nama klien, PIC, kebutuhan awal). -Sales membuat Minutes of Meeting (MOM) jika ada meeting awal, lalu upload ke folder project. | I3: B. Customer Detail -Data lengkap klien diisi di kolom Customer Detail (nama project, kategori, CP, email, nomor HP). -Sales wajib memastikan data ini lengkap sebelum masuk tahap program. | N3: C. Program Detail -Program/Creative membuat konsep & proposal sesuai kebutuhan klien. -PM mengisi kategori event, program, venue, tanggal mulai & selesai. -Draft proposal dilampirkan di folder project, link dicatat di kolom workflow. | U3: D. Progress Detail -Proposal yang sudah jadi dikirim ke klien → status dicatat (Quotation Sent). -Nomor quotation, tanggal, dan status (Pending, Won, Lost) wajib diisi. -Jika deal → upload file kontrak / signed file ke folder project, update status “Signed”. -Jika batal → isi alasan pembatalan. | AB3: E. Instrument -PM bersama tim checklist kebutuhan teknis (venue, catering, stage, multimedia, dll). -Status kesiapan dicatat di kolom Instrument. | AI3: F. Payment Detail -Finance mengisi estimasi budget di kolom Budget (Rp). -Finance membuat jadwal pembayaran (DP, termin, pelunasan). -Status invoice dan pembayaran wajib diupdate secara real-time. -Jika ada keterlambatan, Finance follow up & catat di kolom Note. | AO3: G. Dokumentasi -Tim dokumentasi wajib menyimpan semua hasil dokumentasi di folder drive. -Link foto, video, teaser, dan media sosial (IG/YouTube) dicatat di workflow.
B5: INQ Date | C5: Section | D5: INQ By | E5: Sales | F5: PO | G5: PM | H5: MoM | I5: Company Name | J5: Customer Category | K5: CP | L5: Phone Number | M5: Email | N5: Event Category | O5: Prog | P5: QTY | Q5: Venue | R5: Dur' | S5: Event Date Start | T5: Event Date End | U5: Milestone | V5: Quotation Date | W5: Quotation Number | X5: Quotation Status | Y5: Program Status | Z5: Signed File | AA5: Cancel Reason | AB5: CL | AC5: ROS | AD5: CK | AE5: PNL | AF5: PF | AG5: Matrix | AH5: Note | AI5: Budget (Rp) | AK5: Payment Schadule | AL5: INVOICE Status | AM5: Payment Status | AN5: Project Status | AO5: Link Photo | AP5: Link Video | AQ5: Link Teaser | AR5: IG | AS5: YT
B6: 45663 | C6: OS | D6: Direct | F6: JIP | G6: OME | I6: Golden Rama Travel JKT | J6: Corporate | N6: Employee Gathering | O6: TB | P6: 7 | Q6: R Hotel Rancamaya | R6: =if(ISBLANK($T6),"",$T6-$S6+1) -> 1 | S6: 45664 | T6: 45664 | U6: =if(W6="","", S6-V6 & " days") -> 1 days | V6: 45663 | W6: P006 | X6: Cancel | Y6: Cancel | AA6: No Response | AB6: TRUE | AC6: FALSE | AD6: FALSE | AE6: TRUE | AF6: FALSE | AG6: FALSE | AI6: 6660000 | AR6: FALSE | AS6: FALSE
B7: 45663 | C7: OS | D7: Direct | F7: JIP | G7: OME | I7: PT Binareka Tatamandiri | J7: Corporate | K7: Mrs. Yenni | L7: +62 813 1915 6490 | N7: Entertainment | O7: ENT | P7: 25 | Q7: Royal Tulip Gunung Geulis | R7: =if(ISBLANK($T7),"",$T7-$S7+1) -> 1 | S7: 45664 | T7: 45664 | U7: =if(W7="","", S7-V7 & " days") -> 1 days | V7: 45663 | W7: P009 | X7: Signed & Deal | Y7: Confirm | AA7: - | AB7: TRUE | AC7: TRUE | AD7: TRUE | AE7: TRUE | AF7: FALSE | AG7: TRUE | AI7: 7500000 | AJ7: =AI7 -> 7500000 | AK7: Paid | AL7: Paid | AM7: Paid | AN7: Closed | AR7: TRUE | AS7: FALSE
B8: 45631 | C8: OS | D8: Hotel | E8: Maria | F8: JIP | G8: OME | I8: PT Binareka Tatamandiri | J8: Corporate | K8: Mrs. Yenni | L8: +62 813 1915 6490 | N8: Employee Gathering | O8: RFT | P8: 25 | Q8: Syifa Adventure Rafting | R8: =if(ISBLANK($T8),"",$T8-$S8+1) -> 1 | S8: 45665 | T8: 45665 | U8: =if(W8="","", S8-V8 & " days") -> 34 days | V8: 45631 | W8: P008 | X8: Signed & Deal | Y8: Confirm | AA8: - | AB8: TRUE | AC8: TRUE | AD8: TRUE | AE8: TRUE | AF8: FALSE | AG8: TRUE | AI8: 12626250 | AJ8: =AI8 -> 12626250 | AK8: Paid | AL8: Paid | AM8: Paid | AN8: Closed | AO8: https://drive.google.com/drive/folders/1-hacH_MoKZTyj9z0iLhVNKVcfEs5SYOv?usp=sharing | AQ8: https://www.instagram.com/onespiritasia/reel/DOz2rL1kodS/ | AR8: TRUE | AS8: FALSE
B9: 45663 | C9: OS | D9: Partner | E9: Linda | F9: JIP | G9: OME | I9: DPRD Banten | J9: Goverment | K9: Mrs. Linda | L9: +62 877-7770-7115 | N9: Employee Gathering | O9: RFT | P9: 15 | Q9: Syifa Adventure Rafting | R9: =if(ISBLANK($T9),"",$T9-$S9+1) -> 1 | S9: 45665 | T9: 45665 | U9: =if(W9="","", S9-V9 & " days") -> 2 days | V9: 45663 | W9: P005 | X9: Signed & Deal | Y9: Confirm | AA9: - | AB9: TRUE | AC9: TRUE | AD9: TRUE | AE9: TRUE | AF9: FALSE | AG9: TRUE | AI9: 4200000 | AJ9: =AI9 -> 4200000 | AK9: Paid | AL9: Paid | AM9: Paid | AN9: Closed | AO9: https://drive.google.com/drive/folders/1fv2kALZPjBrLNY8ilmc52dU_CcVBsGin?usp=sharing | AQ9: https://www.instagram.com/onespiritasia/reel/DEhOFIxyZ1z/ | AR9: TRUE | AS9: FALSE
B10: 45661 | C10: OS | D10: Hotel | E10: Hera | F10: SYS | G10: SYS | I10: Mrs Yani | J10: Other | K10: Mrs. Yani | L10: +62857-1930-3666 | N10: Entertainment | O10: ENT | P10: 50 | Q10: Luminor Hotel Bogor | R10: =if(ISBLANK($T10),"",$T10-$S10+1) -> 1 | S10: 45668 | T10: 45668 | U10: =if(W10="","", S10-V10 & " days") -> 7 days | V10: 45661 | W10: P003 | X10: Cancel | Y10: Cancel | AA10: Budget | AB10: TRUE | AC10: FALSE | AD10: FALSE | AE10: FALSE | AF10: FALSE | AG10: FALSE | AI10: 44500000 | AR10: FALSE | AS10: FALSE
B11: 45667 | C11: OS | D11: Hotel | E11: Nanda | F11: JIP | G11: TF | I11: PGN GAGAS | J11: Goverment | K11: Mrs. Firly | L11: +62 813- 8230-1414 | N11: Employee Gathering | O11: Full Arrangement | P11: 40 | Q11: Alana Sentul | R11: =if(ISBLANK($T11),"",$T11-$S11+1) -> 3 | S11: 45672 | T11: 45674 | U11: =if(W11="","", S11-V11 & " days") -> 5 days | V11: 45667 | W11: P015 | X11: Signed & Deal | Y11: Confirm | AA11: - | AB11: TRUE | AC11: TRUE | AD11: TRUE | AE11: TRUE | AF11: FALSE | AG11: TRUE | AI11: 166349319 | AJ11: =AI11 -> 166349319 | AK11: Paid | AL11: Paid | AM11: Paid | AN11: Closed | AQ11: https://www.instagram.com/onespiritasia/reel/DGKVoHozZvI/ | AR11: TRUE | AS11: FALSE
B12: 45569 | C12: OS | D12: Hotel | E12: Maria | F12: JIP | G12: BR | I12: PT Acer Indonesia | J12: Corporate | K12: Mr. Inyo Kusoy | L12: +62 813-4064-2559 | N12: Employee Gathering | O12: TB - Scavenger Hunt | P12: 140 | Q12: Lap. Leuwi Asih, Hutan Hujan, Royal Tulip | R12: =if(ISBLANK($T12),"",$T12-$S12+1) -> 1 | S12: 45674 | T12: 45674 | U12: =if(W12="","", S12-V12 & " days") -> 105 days | V12: 45569 | W12: P001 | X12: Signed & Deal | Y12: Confirm | AA12: - | AB12: TRUE | AC12: TRUE | AD12: TRUE | AE12: TRUE | AF12: FALSE | AG12: TRUE | AI12: 69406288 | AJ12: 69406288 | AK12: Paid | AL12: Paid | AM12: Paid | AN12: Closed | AO12: https://drive.google.com/drive/folders/1aCJrohtxDWHPEG2Pca8w5ypqgoE7m625?usp=sharing | AQ12: https://www.instagram.com/onespiritasia/reel/DE9k1lQSMNu/ | AR12: TRUE | AS12: FALSE
B13: 45643 | C13: OS | D13: Hotel | E13: Yulia | F13: JIP | G13: TF | I13: PT Energy Unggu Persada | J13: Corporate | K13: Mr. Fortune | N13: Production | O13: Production | Q13: Royal Tulip Gunung Geulis | R13: =if(ISBLANK($T13),"",$T13-$S13+1) -> 2 | S13: 45674 | T13: 45675 | U13: =if(W13="","", S13-V13 & " days") -> 31 days | V13: 45643 | W13: P026 | X13: Signed & Deal | Y13: Confirm | AB13: TRUE | AC13: TRUE | AD13: TRUE | AE13: TRUE | AF13: FALSE | AG13: TRUE | AI13: 79838200 | AJ13: 79838200 | AK13: Paid | AL13: Paid | AM13: Paid | AN13: Closed | AR13: FALSE | AS13: FALSE
B14: 45664 | C14: OS | D14: Hotel | F14: JIP | G14: OME | I14: PT Infinite Business Synergy | J14: Corporate | K14: Mrs. Resha | L14: +62 877-7821-3038 | N14: Employee Gathering | O14: TB | P14: 40 | Q14: Pesona Alam | R14: =if(ISBLANK($T14),"",$T14-$S14+1) -> 1 | S14: 45674 | T14: 45674 | U14: =if(W14="","", S14-V14 & " days") -> 10 days | V14: 45664 | W14: P012 | X14: Cancel | Y14: Cancel | AA14: Internal Reason | AB14: TRUE | AC14: FALSE | AD14: FALSE | AE14: FALSE | AF14: FALSE | AG14: FALSE | AI14: 21645000 | AR14: FALSE | AS14: FALSE
B15: 45665 | C15: LS | D15: Hotel | E15: Roy (Bromelia) | F15: JIP | G15: SB | I15: KB Data System Indonesia | J15: Corporate | K15: Mr. Kimi | L15: +62 878-7323-4949 | N15: Employee Gathering | O15: FG | P15: 42 | Q15: Bromelia | R15: =if(ISBLANK($T15),"",$T15-$S15+1) -> 1 | S15: 45674 | T15: 45674 | U15: =if(W15="","", S15-V15 & " days") -> 9 days | V15: 45665 | W15: P021 | X15: Signed & Deal | Y15: Confirm | AB15: TRUE | AC15: TRUE | AD15: TRUE | AE15: TRUE | AF15: FALSE | AG15: TRUE | AI15: 4620000 | AJ15: =AI15 -> 4620000 | AK15: Paid | AL15: Paid | AM15: Paid | AN15: Closed | AR15: FALSE | AS15: FALSE
B16: 45672 | C16: LS | D16: Hotel | E16: Opik | F16: JIP | G16: OME | I16: PT Mandiri Tunas Finance | J16: Corporate | K16: Mrs. Nabila | L16: +62 812-9669-7498 | N16: Employee Gathering | O16: TB | P16: 26 | Q16: Lenirra Villa & Resto | R16: =if(ISBLANK($T16),"",$T16-$S16+1) -> 1 | S16: 45674 | T16: 45674 | U16: =if(W16="","", S16-V16 & " days") -> 2 days | V16: 45672 | W16: P025 | X16: Signed & Deal | Y16: Confirm | AB16: TRUE | AC16: TRUE | AD16: TRUE | AE16: TRUE | AF16: FALSE | AG16: TRUE | AI16: 2600000 | AJ16: =AI16 -> 2600000 | AK16: Paid | AL16: Paid | AM16: Paid | AN16: Closed | AR16: FALSE | AS16: FALSE
B17: 45672 | C17: LS | D17: Hotel | E17: Opick | F17: JIP | G17: SB | I17: PT Hardana WIdya Mahir | J17: Corporate | K17: Mrs Dinda | L17: +62 895-2343-1883 | N17: Other | O17: OFR | Q17: Lenirra Villa& resto | R17: =if(ISBLANK($T17),"",$T17-$S17+1) -> 2 | S17: 45674 | T17: 45675 | U17: =if(W17="","", S17-V17 & " days") -> 3 days | V17: 45671 | W17: P068 | X17: Signed & Deal | Y17: Confirm | AB17: TRUE | AC17: TRUE | AD17: TRUE | AE17: TRUE | AF17: FALSE | AG17: TRUE | AI17: 3500000 | AJ17: =AI17 -> 3500000 | AK17: Paid | AL17: Paid | AM17: Paid | AN17: Closed | AO17: DOKUMENTASI PT.HARDANA WIDYA MAHIR | AR17: FALSE | AS17: FALSE
B18: 45670 | C18: LS | D18: Hotel | E18: Puji | F18: JIP | G18: SB | I18: Mahakarya Adi Indonesia | J18: Corporate | K18: Mrs. Bella Arifah | L18: +62 817-7679-9928 | N18: Employee Gathering | O18: FG | P18: 65 | Q18: The Botanica Sanctuary | R18: =if(ISBLANK($T18),"",$T18-$S18+1) -> 1 | S18: 45679 | T18: 45679 | U18: =if(W18="","", S18-V18 & " days") -> 9 days | V18: 45670 | W18: P027 | X18: Signed & Deal | Y18: Confirm | AB18: TRUE | AC18: TRUE | AD18: TRUE | AE18: TRUE | AF18: FALSE | AG18: TRUE | AI18: 14300000 | AJ18: =AI18 -> 14300000 | AK18: Paid | AL18: Paid | AM18: Paid | AN18: Closed | AO18: https://drive.google.com/drive/folders/1CtJvNSkqO46UgP2HMHa_LnVbhXdE7RK6?usp=sharing | AR18: FALSE | AS18: FALSE
B19: 45663 | C19: OS | D19: Hotel | F19: JIP | G19: OME | I19: OLX | J19: Corporate | K19: Tannya | L19: +62 896-7218-5308 | N19: Employee Gathering | O19: TB | P19: 132 | Q19: Aston Ciloto | R19: =if(ISBLANK($T19),"",$T19-$S19+1) -> 1 | S19: 45680 | T19: 45680 | U19: =if(W19="","", S19-V19 & " days") -> 17 days | V19: 45663 | W19: P013 | X19: Cancel | Y19: Cancel | AA19: Competitor | AB19: TRUE | AC19: FALSE | AD19: FALSE | AE19: FALSE | AF19: FALSE | AG19: FALSE | AI19: 27838800 | AR19: FALSE | AS19: FALSE
B20: 45668 | C20: OS | D20: Hotel | F20: SYS | G20: SYS | I20: PT Taren Satiu Tuju | J20: Corporate | K20: Mr. Rizqi | L20: 0812-1271-1888 | N20: Production | O20: Production | P20: 250 | Q20: MNC Lido Lake Resort | R20: =if(ISBLANK($T20),"",$T20-$S20+1) -> 2 | S20: 45681 | T20: 45682 | U20: =if(W20="","", S20-V20 & " days") -> 15 days | V20: 45666 | W20: P019 | X20: Cancel | Y20: Cancel | AA20: No Response | AB20: TRUE | AC20: FALSE | AD20: FALSE | AE20: FALSE | AF20: FALSE | AG20: FALSE | AI20: 30834823 | AR20: FALSE | AS20: FALSE
B21: 45671 | C21: LS | D21: Hotel | E21: Opik | F21: JIP | G21: SB | I21: PT Century Distribution System Indonesia | J21: Corporate | K21: Mrs Rahma | L21: +62 856-9495-5900 | N21: Employee Gathering | O21: TB | P21: 35 | Q21: Lenirra Villa & Resto | R21: =if(ISBLANK($T21),"",$T21-$S21+1) -> 1 | S21: 45682 | T21: 45682 | U21: =if(W21="","", S21-V21 & " days") -> 11 days | V21: 45671 | W21: P028 | X21: Signed & Deal | Y21: Confirm | AB21: TRUE | AC21: TRUE | AD21: TRUE | AE21: TRUE | AF21: FALSE | AG21: TRUE | AI21: 3500000 | AJ21: =AI21 -> 3500000 | AK21: Paid | AL21: Paid | AM21: Paid | AN21: Closed | AO21: https://drive.google.com/drive/folders/1mE1BpaeyOE5rUqgy7tk658vqcjWkzj5p?usp=sharing | AQ21: https://www.instagram.com/onespiritasia/reel/DLG6daKyvEd/ | AR21: TRUE | AS21: FALSE
B22: 45671 | C22: LS | D22: Hotel | E22: Opik | F22: JIP | G22: SB | I22: PT Century Distribution System Indonesia | J22: Corporate | K22: Mrs Rahma | L22: +62 856-9495-5901 | N22: Employee Gathering | O22: Others | P22: 35 | Q22: Lenirra Villa & Resto | R22: =if(ISBLANK($T22),"",$T22-$S22+1) -> 2 | S22: 45682 | T22: 45683 | U22: =if(W22="","", S22-V22 & " days") -> 11 days | V22: 45671 | W22: P029 | X22: Signed & Deal | Y22: Confirm | AB22: TRUE | AC22: TRUE | AD22: TRUE | AE22: TRUE | AF22: FALSE | AG22: TRUE | AI22: 4000000 | AJ22: =AI22 -> 4000000 | AK22: Paid | AL22: Paid | AM22: Paid | AN22: Closed | AO22: https://drive.google.com/drive/folders/1mE1BpaeyOE5rUqgy7tk658vqcjWkzj5p?usp=sharing | AQ22: https://www.instagram.com/onespiritasia/reel/DLG6daKyvEd/ | AR22: TRUE | AS22: FALSE
B23: 45672 | C23: OS | D23: Hotel | F23: JIP | G23: TF | I23: APARI | J23: Corporate | K23: Mrs. Lela | L23: 62 823-6200-4881 | N23: Employee Gathering | O23: RFT | P23: 30 | Q23: Alamanda Rafting | R23: =if(ISBLANK($T23),"",$T23-$S23+1) -> 1 | S23: 45689 | T23: 45689 | U23: =if(W23="","", S23-V23 & " days") -> 17 days | V23: 45672 | W23: P023 | X23: Cancel | Y23: Cancel | AA23: No Response | AB23: TRUE | AC23: FALSE | AD23: FALSE | AE23: FALSE | AF23: FALSE | AG23: FALSE | AI23: 19369500 | AR23: FALSE | AS23: FALSE
B24: 45681 | C24: OS | D24: Partner | F24: JIP | G24: BR | I24: FMIPA IPB | J24: Goverment | K24: Mrs. Ati | L24: +62 812-8974-499 | N24: Employee Gathering | O24: TB | P24: 20 | Q24: Neo Hotel Sentul | R24: =if(ISBLANK($T24),"",$T24-$S24+1) -> 1 | S24: 45689 | T24: 45689 | U24: =if(W24="","", S24-V24 & " days") -> 8 days | V24: 45681 | W24: P033 | X24: Cancel | Y24: Cancel | AA24: No Response | AB24: FALSE | AC24: FALSE | AD24: FALSE | AE24: FALSE | AF24: FALSE | AG24: FALSE | AI24: 9500000 | AR24: FALSE | AS24: FALSE
B25: 45666 | C25: LS | D25: Repeater | F25: JIP | G25: SB | I25: Telkom Property | J25: Corporate | K25: Mrs. Farha | L25: +62 813-1905-9828 | N25: Employee Gathering | O25: Production | Q25: Auditorium Telkom Landmark Tower | R25: =if(ISBLANK($T25),"",$T25-$S25+1) -> 2 | S25: 45691 | T25: 45692 | U25: =if(W25="","", S25-V25 & " days") -> 25 days | V25: 45666 | W25: P014 | X25: Signed & Deal | Y25: Confirm | AA25: - | AB25: TRUE | AC25: TRUE | AD25: TRUE | AE25: TRUE | AF25: FALSE | AG25: TRUE | AI25: 39150000 | AJ25: =AI25 -> 39150000 | AK25: Paid | AL25: Paid | AM25: Paid | AN25: Closed | AR25: FALSE | AS25: FALSE
B26: 45553 | C26: LS | D26: Repeater | F26: RA | G26: SB | I26: TK Nurul Huda CIbuluh | J26: Student | K26: Mrs TIni | L26: +62 857 1040 3573 | N26: Tour | O26: Study tour | P26: 91 | Q26: TSI | R26: =if(ISBLANK($T26),"",$T26-$S26+1) -> 1 | S26: 45693 | T26: 45693 | U26: =if(W26="","", S26-V26 & " days") -> 140 days | V26: 45553 | W26: P038 | X26: Signed & Deal | Y26: Confirm | AB26: TRUE | AC26: TRUE | AD26: TRUE | AE26: TRUE | AF26: FALSE | AG26: TRUE | AI26: 37100000 | AJ26: =AI26 -> 37100000 | AK26: Paid | AL26: Paid | AM26: Paid | AN26: Closed | AO26: https://drive.google.com/drive/folders/17EfwWcAsKZUR6-OaT86CtLuYMkg_Y3W2 | AQ26: https://www.instagram.com/onespiritasia/reel/DFwwnT6zJnt/ | AR26: TRUE | AS26: FALSE
B27: 45672 | C27: OS | D27: Hotel | E27: Ibu Beta | F27: JIP | G27: OME | I27: PT Asuransi Raksa Pratikara | J27: Corporate | K27: Mrs. Susy | L27: +62 816 976 101 | N27: Entertainment | O27: ENT | Q27: Royal Tulip Gunung Geulis | R27: =if(ISBLANK($T27),"",$T27-$S27+1) -> 1 | S27: 45694 | T27: 45694 | U27: =if(W27="","", S27-V27 & " days") -> 22 days | V27: 45672 | W27: P024 | X27: Signed & Deal | Y27: Confirm | AB27: TRUE | AC27: TRUE | AD27: TRUE | AE27: TRUE | AF27: FALSE | AG27: TRUE | AI27: 13000000 | AJ27: =AI27 -> 13000000 | AK27: Paid | AL27: Paid | AM27: Paid | AN27: Closed | AR27: FALSE | AS27: FALSE
B28: 45678 | C28: OS | D28: Repeater | F28: BR | G28: BR | I28: Daimler Truck - Soft SOP | J28: Corporate | K28: Mrs. Yessi | L28: +62 813-2717-0256 | N28: Production | O28: Production | Q28: Cikarang - Bekasi | R28: =if(ISBLANK($T28),"",$T28-$S28+1) -> 2 | S28: 45694 | T28: 45695 | U28: =if(W28="","", S28-V28 & " days") -> 16 days | V28: 45678 | W28: P032 | X28: Signed & Deal | Y28: Confirm | AB28: FALSE | AC28: FALSE | AD28: TRUE | AE28: TRUE | AF28: FALSE | AG28: TRUE | AI28: 51139176 | AJ28: =AI28 -> 51139176 | AK28: Paid | AL28: Paid | AM28: Paid | AN28: Closed | AR28: FALSE | AS28: FALSE
B29: 45663 | C29: OS | D29: Repeater | F29: MWB | G29: TF | I29: PT Sariling | J29: Corporate | K29: Mrs. Yunita Sitanggang | L29: +62 851-5777-8737 | N29: Employee Gathering | O29: TB | P29: 44 | Q29: Bogor/Bandung (TBC) | R29: =if(ISBLANK($T29),"",$T29-$S29+1) -> 2 | S29: 45695 | T29: 45696 | U29: =if(W29="","", S29-V29 & " days") -> 32 days | V29: 45663 | W29: P007 | X29: Cancel | Y29: Cancel | AA29: - | AB29: FALSE | AC29: FALSE | AD29: FALSE | AE29: TRUE | AF29: FALSE | AG29: FALSE | AI29: 75579900 | AR29: FALSE | AS29: FALSE
B30: 45668 | C30: OS | D30: Direct | F30: JIP | G30: SB | I30: Huawei | J30: Corporate | K30: Mrs. Resti | L30: +62 896-6199-6515 | N30: Employee Gathering | O30: Full Arrangement | P30: 93 | Q30: Royal Tulip Gunung Geulis | R30: =if(ISBLANK($T30),"",$T30-$S30+1) -> 2 | S30: 45695 | T30: 45696 | U30: =if(W30="","", S30-V30 & " days") -> 27 days | V30: 45668 | W30: P020 | X30: Cancel | Y30: Cancel | AA30: No Response | AB30: TRUE | AC30: FALSE | AD30: FALSE | AE30: FALSE | AF30: FALSE | AG30: FALSE | AI30: 426244995 | AR30: FALSE | AS30: FALSE
B31: 45660 | C31: OS | D31: Web | F31: UT | G31: UT | I31: PT Mega Waja Corporindo | J31: Corporate | K31: Mrs. Septi | N31: Employee Gathering | O31: Others | P31: 20 | Q31: Bogor | R31: =if(ISBLANK($T31),"",$T31-$S31+1) -> 2 | S31: 45696 | T31: 45697 | U31: =if(W31="","", S31-V31 & " days") -> 36 days | V31: 45660 | W31: P042 | X31: Cancel | Y31: Cancel | AB31: FALSE | AC31: FALSE | AD31: FALSE | AE31: FALSE | AF31: FALSE | AG31: FALSE | AI31: 36385800 | AR31: FALSE | AS31: FALSE
B32: 45672 | C32: OS | D32: Direct | F32: JIP | G32: BR | I32: BNI Jakarta | J32: Corporate | K32: Mrs. Risa | L32: +61 434 548 598 | N32: Employee Gathering | O32: TB - Scavenger Hunt | P32: 130 | Q32: Jogjakarta | R32: =if(ISBLANK($T32),"",$T32-$S32+1) -> 2 | S32: 45696 | T32: 45697 | U32: =if(W32="","", S32-V32 & " days") -> 24 days | V32: 45672 | W32: P030 | X32: Cancel | Y32: Cancel | AB32: TRUE | AC32: FALSE | AD32: FALSE | AE32: FALSE | AF32: FALSE | AG32: FALSE | AI32: 200069153 | AR32: FALSE | AS32: FALSE
B33: 45688 | C33: LS | D33: Direct | F33: BR | G33: BR | I33: RS Pertamina | J33: Corporate | K33: Mrs. Oche | L33: +62 818-0865-7356 | N33: Employee Gathering | O33: TB | P33: 60 | Q33: Bigland | R33: =if(ISBLANK($T33),"",$T33-$S33+1) -> 1 | S33: 45696 | T33: 45696 | U33: =if(W33="","", S33-V33 & " days") -> 7 days | V33: 45689 | W33: P043 | X33: Cancel | Y33: Cancel | AA33: Internal Reason | AB33: FALSE | AC33: FALSE | AD33: FALSE | AE33: FALSE | AF33: FALSE | AG33: FALSE | AI33: 9000000 | AR33: FALSE | AS33: FALSE
B34: 45681 | C34: OS | D34: Hotel | E34: Nanda | F34: JIP | G34: SB | I34: PLN IP UBP Kamojang (Batch 1) | J34: Goverment | K34: Mr Mishbah | L34: +62 822 3449 9535 | N34: Other | O34: Trekking | P34: 25 | Q34: Leuwi Asih | R34: =if(ISBLANK($T34),"",$T34-$S34+1) -> 1 | S34: 45699 | T34: 45699 | U34: =if(W34="","", S34-V34 & " days") -> 18 days | V34: 45681 | W34: P039 | X34: Signed & Deal | Y34: Confirm | Z34: https://drive.google.com/file/d/1jp6i0BvqlQfrwQcJBuGIF2oTErSZgcfa/view?usp=drive_link | AB34: TRUE | AC34: TRUE | AD34: TRUE | AE34: TRUE | AF34: FALSE | AG34: TRUE | AI34: 14957250 | AJ34: =AI34 -> 14957250 | AK34: Paid | AL34: Paid | AM34: Paid | AN34: Closed | AO34: https://drive.google.com/drive/folders/1zMDuPh1E2kf6Yd4UtQruXN9u1f390I37?usp=sharing | AR34: TRUE | AS34: FALSE | AT34: Payment LS 14 Days
B35: 45666 | C35: OS | D35: Repeater | F35: JIP | G35: TF | I35: PT Sinergi Wahana Gemilang | J35: Corporate | K35: Mrs. Tiwi | L35: +62 812-8059-2908 | N35: Employee Gathering | O35: Full Arrangement | P35: 120 | Q35: Hotel Santika Kuningan | R35: =if(ISBLANK($T35),"",$T35-$S35+1) -> 2 | S35: 45700 | T35: 45701 | U35: =if(W35="","", S35-V35 & " days") -> 34 days | V35: 45666 | W35: P016 | X35: Signed & Deal | Y35: Confirm | AA35: - | AB35: TRUE | AC35: TRUE | AD35: TRUE | AE35: TRUE | AF35: FALSE | AG35: TRUE | AI35: 25000000 | AJ35: =AI35 -> 25000000 | AK35: Paid | AL35: Paid | AM35: Paid | AN35: Closed | AO35: https://drive.google.com/drive/folders/1BEyJ6Huic6QO3Sz4pVyOBL0y2yCqDv26?usp=sharing | AQ35: https://www.instagram.com/onespiritasia/reel/DGKVoHozZvI/ | AR35: TRUE | AS35: FALSE
B36: 45672 | C36: OS | D36: Hotel | F36: JIP | G36: OME | I36: PT. MC Urban Development Indonesia | J36: Corporate | K36: Mr. Dana Dwi Satria | L36: +62 811 1933 0168 | N36: Employee Gathering | O36: Others | P36: 20 | Q36: Pullman Ciawi | R36: =if(ISBLANK($T36),"",$T36-$S36+1) -> 1 | S36: 45701 | T36: 45701 | U36: =if(W36="","", S36-V36 & " days") -> 29 days | V36: 45672 | W36: P022 | X36: Cancel | Y36: Cancel | AB36: TRUE | AC36: FALSE | AD36: FALSE | AE36: FALSE | AF36: FALSE | AG36: FALSE | AI36: 8000000 | AR36: FALSE | AS36: FALSE
B37: 45681 | C37: OS | D37: Hotel | E37: Nanda | F37: JIP | G37: SB | I37: PLN IP UBP Kamojang ( Batch 2 ) | J37: Goverment | K37: Mr Mishbah | L37: +62 822 3449 9535 | N37: Other | O37: Trekking | P37: 25 | Q37: Leusi Asih | R37: =if(ISBLANK($T37),"",$T37-$S37+1) -> 1 | S37: 45701 | T37: 45701 | U37: =if(W37="","", S37-V37 & " days") -> 20 days | V37: 45681 | W37: P040 | X37: Signed & Deal | Y37: Confirm | Z37: https://drive.google.com/file/d/1PKONQAygQGPxJjNNJEs-p5jYnn4zWhj8/view?usp=drive_link | AB37: TRUE | AC37: TRUE | AD37: TRUE | AE37: TRUE | AF37: FALSE | AG37: TRUE | AI37: 14529900 | AJ37: =AI37 -> 14529900 | AK37: Paid | AL37: Paid | AM37: Paid | AN37: Closed | AO37: https://drive.google.com/drive/folders/1FmBuxbny6KG7Z8QfaFhOUs1t4xwnDMs2?usp=sharing | AR37: TRUE | AS37: FALSE | AT37: Payment LS 14 Days
B38: 45567 | C38: OS | D38: Hotel | F38: JIP | G38: OME | I38: Dharma Wanita BNI Pusat | J38: Corporate | K38: Mrs. Denis | L38: +62 812 8130 412 | N38: Employee Gathering | O38: Others | P38: 120 | Q38: Royal Tulip Gunung Geulis | R38: =if(ISBLANK($T38),"",$T38-$S38+1) -> 1 | S38: 45702 | T38: 45702 | U38: =if(W38="","", S38-V38 & " days") -> 135 days | V38: 45567 | W38: P050 | X38: Cancel | Y38: Cancel | AB38: FALSE | AC38: FALSE | AD38: FALSE | AE38: FALSE | AF38: FALSE | AG38: FALSE | AI38: 97680000 | AR38: FALSE | AS38: FALSE
B39: 45699 | C39: OS | D39: Hotel | F39: JIP | G39: TF | I39: ANTAM | J39: Corporate | K39: Mrs. Wirda | N39: Production | O39: Production | R39: =if(ISBLANK($T39),"",$T39-$S39+1) -> 1 | S39: 45702 | T39: 45702 | U39: =if(W39="","", S39-V39 & " days") -> 3 days | V39: 45699 | W39: P053 | X39: Cancel | Y39: Cancel | AB39: TRUE | AC39: FALSE | AD39: FALSE | AE39: FALSE | AF39: FALSE | AG39: FALSE | AI39: 7104000 | AR39: FALSE | AS39: FALSE
B40: 45665 | C40: OS | D40: Hotel | E40: Puji | F40: JIP | G40: SB | I40: Krakatau Steel | J40: Corporate | K40: Mrs. Dyosferra | L40: +62 877-7431-1499 | N40: Employee Gathering | O40: Production | P40: 30 | Q40: Pesona Alam Resort & Spa | R40: =if(ISBLANK($T40),"",$T40-$S40+1) -> 2 | S40: 45705 | T40: 45706 | U40: =if(W40="","", S40-V40 & " days") -> 40 days | V40: 45665 | W40: P018 | X40: Signed & Deal | Y40: Confirm | AA40: - | AB40: TRUE | AC40: TRUE | AD40: TRUE | AE40: TRUE | AF40: FALSE | AG40: TRUE | AI40: 58000000 | AJ40: =AI40 -> 58000000 | AK40: Paid | AL40: Paid | AM40: Paid | AN40: Closed | AO40: https://drive.google.com/drive/folders/1Y-fvzu1KSj7KptbYLn_7nvDXom35_Wt_?usp=sharing | AQ40: https://www.instagram.com/onespiritasia/reel/DF444cATBiX/ | AR40: TRUE | AS40: FALSE
B41: 45683 | C41: OS | D41: Hotel | F41: JIP | G41: TF | I41: Trakindo | J41: Corporate | K41: Ardi Sobby | L41: 62 811-8010-2950 | N41: Meeting | O41: Production | P41: 50 | Q41: Aston Sentul | R41: =if(ISBLANK($T41),"",$T41-$S41+1) -> 3 | S41: 45705 | T41: 45707 | U41: =if(W41="","", S41-V41 & " days") -> 22 days | V41: 45683 | W41: P036 | X41: Cancel | Y41: Cancel | AB41: TRUE | AC41: FALSE | AD41: FALSE | AE41: FALSE | AF41: FALSE | AG41: FALSE | AI41: Rp296,641,950 | AR41: FALSE | AS41: FALSE
B42: 45645 | C42: OS | D42: Direct | F42: JIP | G42: OME | I42: PERTAABI | J42: Corporate | K42: Mrs. Putri | L42: +62 813-1590-8797 | N42: Production | O42: Production | Q42: Sheraton Grand Jakarta | R42: =if(ISBLANK($T42),"",$T42-$S42+1) -> 1 | S42: 45708 | T42: 45708 | U42: =if(W42="","", S42-V42 & " days") -> 63 days | V42: 45645 | W42: P011 | X42: Signed & Deal | Y42: Confirm | AA42: - | AB42: TRUE | AC42: FALSE | AD42: FALSE | AE42: FALSE | AF42: FALSE | AG42: TRUE | AI42: 89650000 | AJ42: =AI42 -> 89650000 | AK42: Paid | AL42: Paid | AM42: Paid | AN42: Closed | AO42: https://drive.google.com/drive/folders/1QuKPBqPQOu521IdGQp-U4MQNsfEstF6z | AQ42: https://www.instagram.com/onespiritasia/reel/DGULGiiy_Kr/ | AR42: TRUE | AS42: FALSE
B43: 45677 | C43: LS | D43: Repeater | E43: PO by Numan | F43: SBK | G43: SB | I43: Study Tour SMP 18 Goes to Dufan | J43: Student | K43: Mrs. Yani | N43: Tour | O43: Others | P43: 450 | Q43: Taman Impian Jaya Ancol | R43: =if(ISBLANK($T43),"",$T43-$S43+1) -> 1 | S43: 45708 | T43: 45708 | U43: =if(W43="","", S43-V43 & " days") -> 28 days | V43: 45680 | W43: P058 | X43: Signed & Deal | Y43: Confirm | AB43: TRUE | AC43: FALSE | AD43: TRUE | AE43: TRUE | AF43: FALSE | AG43: FALSE | AI43: 126600000 | AJ43: =AI43 -> 126600000 | AK43: Paid | AL43: Paid | AM43: Paid | AN43: Closed | AR43: TRUE | AS43: FALSE
B44: 45705 | C44: LS | D44: Hotel | E44: Rai | F44: JIP | G44: SB | I44: Pertamina | J44: Goverment | N44: Other | O44: FG | P44: 25 | Q44: Lenirra Villa& resto | R44: =if(ISBLANK($T44),"",$T44-$S44+1) -> 1 | S44: 45708 | T44: 45708 | U44: =if(W44="","", S44-V44 & " days") -> 3 days | V44: 45705 | W44: P062 | X44: Signed & Deal | Y44: Confirm | AB44: TRUE | AC44: TRUE | AD44: TRUE | AE44: TRUE | AF44: FALSE | AG44: TRUE | AI44: 3125000 | AJ44: =AI44 -> 3125000 | AK44: Paid | AL44: Paid | AM44: Paid | AN44: Closed | AR44: FALSE | AS44: FALSE
B45: 45663 | C45: OS | D45: Repeater | F45: JIP | G45: TF | I45: Asuransi Etika | J45: Corporate | K45: Mrs. Foni | L45: +62812-83869330 | N45: Employee Gathering | O45: TB | P45: 180 | Q45: TBC | R45: =if(ISBLANK($T45),"",$T45-$S45+1) -> 2 | S45: 45709 | T45: 45710 | U45: =if(W45="","", S45-V45 & " days") -> 46 days | V45: 45663 | W45: P004 | X45: Cancel | Y45: Cancel | AA45: - | AB45: TRUE | AC45: FALSE | AD45: FALSE | AE45: FALSE | AF45: FALSE | AG45: FALSE | AI45: 100455000 | AR45: FALSE | AS45: FALSE
B46: 45672 | C46: OS | D46: Direct | F46: JIP | G46: BR | I46: Purwakarta | J46: Corporate | K46: Mrs. Dini | L46: +62 815-8287-313 | N46: Employee Gathering | O46: Inflatable Race | P46: 100 | Q46: Purwakarta | R46: =if(ISBLANK($T46),"",$T46-$S46+1) -> 2 | S46: 45709 | T46: 45710 | U46: =if(W46="","", S46-V46 & " days") -> 37 days | V46: 45672 | W46: P031 | X46: Cancel | Y46: Cancel | AB46: FALSE | AC46: FALSE | AD46: FALSE | AE46: FALSE | AF46: FALSE | AG46: FALSE | AI46: 150000000 | AR46: FALSE | AS46: FALSE
B47: 45682 | C47: OS | D47: Partner | E47: Yogi - DNA | F47: BR | G47: BR | I47: DNA | J47: Corporate | N47: Employee Gathering | O47: TB | P47: 100 | Q47: Bogor | R47: =if(ISBLANK($T47),"",$T47-$S47+1) -> 2 | S47: 45709 | T47: 45710 | U47: =if(W47="","", S47-V47 & " days") -> 27 days | V47: 45682 | W47: P037 | X47: Cancel | Y47: Cancel | AA47: Internal Reason | AB47: FALSE | AC47: FALSE | AD47: FALSE | AE47: FALSE | AF47: FALSE | AG47: FALSE | AI47: 70000000 | AR47: FALSE | AS47: FALSE
B48: 45693 | C48: OS | D48: Hotel | E48: Novalita (Royal tulip) | F48: JIP | G48: OME | I48: Smartfren Sabang | J48: Corporate | K48: Mrs. Mimie | L48: +62 888 1853 295 | N48: Employee Gathering | O48: TB | P48: 170 | Q48: JSI Resort | R48: =if(ISBLANK($T48),"",$T48-$S48+1) -> 1 | S48: 45709 | T48: 45709 | U48: =if(W48="","", S48-V48 & " days") -> 16 days | V48: 45693 | W48: P054 | X48: Signed & Deal | Y48: Confirm | AB48: TRUE | AC48: TRUE | AD48: TRUE | AE48: FALSE | AF48: FALSE | AG48: TRUE | AI48: 169275000 | AJ48: =AI48 -> 169275000 | AK48: Paid | AL48: Paid | AO48: https://drive.google.com/drive/folders/1sx2t0UYlbGU8qQWXBFQaD2A_jnLo9dA8?usp=sharing | AQ48: https://www.instagram.com/onespiritasia/reel/DGZTeSJTn46/ | AR48: TRUE | AS48: FALSE
B49: 45695 | C49: LS | D49: Hotel | E49: Opick | F49: JIP | G49: UT | I49: PT Argha Karya Prima | J49: Corporate | K49: Mrs. Mirah | L49: +62 812 8753 0500 | N49: Employee Gathering | O49: TB | P49: 31 | Q49: Lenirra Villa& resto | R49: =if(ISBLANK($T49),"",$T49-$S49+1) -> 1 | S49: 45709 | T49: 45709 | U49: =if(W49="","", S49-V49 & " days") -> 13 days | V49: 45696 | W49: P060 | X49: Signed & Deal | Y49: Confirm | AB49: TRUE | AC49: TRUE | AD49: TRUE | AE49: TRUE | AF49: FALSE | AG49: TRUE | AI49: 3100000 | AJ49: =AI49 -> 3100000 | AK49: Paid | AL49: Paid | AM49: Paid | AN49: Closed | AR49: FALSE | AS49: FALSE
B50: 45705 | C50: LS | D50: Direct | E50: Opick | F50: JIP | G50: SB | I50: PT Argha Karya Prima | J50: Corporate | K50: Mrs. Mirah | L50: +62 812 8753 0500 | N50: Employee Gathering | O50: Others | P50: 31 | Q50: Lenirra Villa& resto | R50: =if(ISBLANK($T50),"",$T50-$S50+1) -> 2 | S50: 45709 | T50: 45710 | U50: =if(W50="","", S50-V50 & " days") -> 8 days | V50: 45701 | W50: P063 | X50: Signed & Deal | Y50: Confirm | AB50: TRUE | AC50: TRUE | AD50: TRUE | AE50: TRUE | AF50: FALSE | AG50: TRUE | AI50: 3000000 | AJ50: =AI50 -> 3000000 | AK50: Paid | AL50: Paid | AM50: Paid | AN50: Closed | AO50: https://drive.google.com/drive/folders/1lz7TaxXidGCauIKO7_qjS3TmGESzugcu?usp=sharing | AR50: FALSE | AS50: FALSE
B51: 45760 | C51: OS | D51: Hotel | F51: JIP | G51: BR | I51: BPJS Ketenagakerjaan Pusat | J51: Corporate | K51: Mrs. Sofia | L51: +62 812-1072-573 | N51: Employee Gathering | O51: Production | P51: 114 | Q51: Aston Bogor | R51: =if(ISBLANK($T51),"",$T51-$S51+1) -> 1 | S51: 45709 | T51: 45709 | U51: =if(W51="","", S51-V51 & " days") -> 8 days | V51: 45701 | W51: P057 | X51: Signed & Deal | Y51: Confirm | AB51: FALSE | AC51: FALSE | AD51: FALSE | AE51: FALSE | AF51: FALSE | AG51: TRUE | AI51: 34996913 | AJ51: =AI51 -> 34996913 | AK51: Paid | AL51: Paid | AM51: Paid | AN51: Closed | AR51: FALSE | AS51: FALSE
B52: 45709 | C52: LS | D52: Hotel | E52: Opick | F52: JIP | G52: SB | I52: BNP Parimbas | J52: Goverment | N52: Other | O52: TB | P52: 23 | Q52: Lenirra Villa& resto | R52: =if(ISBLANK($T52),"",$T52-$S52+1) -> 1 | S52: 45710 | T52: 45710 | U52: =if(W52="","", S52-V52 & " days") -> 0 days | V52: 45710 | W52: P067 | X52: Signed & Deal | Y52: Confirm | AB52: TRUE | AC52: TRUE | AD52: TRUE | AE52: TRUE | AF52: FALSE | AG52: TRUE | AI52: 2300000 | AJ52: =AI52 -> 2300000 | AK52: Paid | AL52: Paid | AM52: Paid | AN52: Closed | AR52: FALSE | AS52: FALSE
B53: 45695 | C53: OS | D53: Hotel | E53: Zia | F53: JIP | G53: SB | I53: PT. Jasa Prima Logistik BULOG | J53: Corporate | K53: Mr. Arham | L53: +62 811 4614 164 | N53: Employee Gathering | O53: TB | P53: 110 | Q53: Heha & Pesona | R53: =if(ISBLANK($T53),"",$T53-$S53+1) -> 1 | S53: 45711 | T53: 45711 | U53: =if(W53="","", S53-V53 & " days") -> 16 days | V53: 45695 | W53: P045 | X53: Signed & Deal | Y53: Confirm | Z53: https://acrobat.adobe.com/id/urn:aaid:sc:AP:6d0e2d53-fb50-46fa-afbd-fc8325f01ac2 | AB53: TRUE | AC53: TRUE | AD53: TRUE | AE53: TRUE | AF53: FALSE | AG53: TRUE | AI53: 33499800 | AJ53: =AI53 -> 33499800 | AK53: Paid | AL53: Paid | AM53: Paid | AN53: Closed | AR53: TRUE | AS53: FALSE
B54: 45710 | C54: OS | D54: Hotel | F54: JIP | G54: SB | I54: Jasa Prima Logistik Bulog | J54: Corporate | K54: Mr. Arham | L54: +62 811 4614 164 | N54: Production | O54: Production | P54: 86 | Q54: Pesona Alam | R54: =if(ISBLANK($T54),"",$T54-$S54+1) -> 3 | S54: 45711 | T54: 45713 | U54: =if(W54="","", S54-V54 & " days") -> 1 days | V54: 45710 | W54: P069 | X54: Signed & Deal | Y54: Confirm | AB54: TRUE | AC54: TRUE | AD54: TRUE | AE54: TRUE | AF54: FALSE | AG54: FALSE | AI54: 2800000 | AJ54: =AI54 -> 2800000 | AK54: Paid | AL54: Paid | AM54: Paid | AN54: Closed | AO54: https://drive.google.com/drive/folders/1lz7TaxXidGCauIKO7_qjS3TmGESzugcu | AR54: FALSE | AS54: FALSE
B55: 45698 | C55: OS | D55: Direct | F55: JIP | G55: UT | I55: PT Mahitala Ingkeng Gemah | J55: Corporate | K55: Mr. Zherfin | L55: +62 852-1978-6669 | N55: Employee Gathering | O55: RFT | P55: 24 | Q55: Syifa Adventure Rafting | R55: =if(ISBLANK($T55),"",$T55-$S55+1) -> 4 | S55: 45713 | T55: 45716 | U55: =if(W55="","", S55-V55 & " days") -> 15 days | V55: 45698 | W55: P049 | X55: Cancel | Y55: Cancel | AB55: FALSE | AC55: FALSE | AD55: FALSE | AE55: FALSE | AF55: FALSE | AG55: FALSE | AI55: 12645000 | AR55: FALSE | AS55: FALSE
B56: 45705 | C56: OS | D56: Hotel | F56: JIP | G56: TF | I56: PT Helios Informatika Nusantara | J56: Corporate | K56: Mrs Galih | L56: +62 859-5902-8373 | N56: Employee Gathering | O56: TB | P56: 30 | Q56: Royal Tulip | R56: =if(ISBLANK($T56),"",$T56-$S56+1) -> 1 | S56: 45714 | T56: 45714 | U56: =if(W56="","", S56-V56 & " days") -> 9 days | V56: 45705 | W56: P061 | X56: Cancel | Y56: Cancel | AA56: Internal Reason | AB56: TRUE | AC56: TRUE | AD56: FALSE | AE56: FALSE | AF56: FALSE | AG56: FALSE | AI56: 14985000 | AR56: FALSE | AS56: FALSE
B57: 45713 | C57: OS | D57: Hotel | F57: JIP | G57: SB | I57: Jasa Prima Logistik Bulog | J57: Corporate | K57: Mr. Arham | L57: +62 811 4614 164 | N57: Entertainment | O57: ENT | P57: 86 | Q57: Pesona Alam | R57: =if(ISBLANK($T57),"",$T57-$S57+1) -> 1 | S57: 45714 | T57: 45714 | U57: =if(W57="","", S57-V57 & " days") -> 1 days | V57: 45713 | W57: P070 | X57: Signed & Deal | Y57: Confirm | AB57: TRUE | AC57: TRUE | AD57: TRUE | AE57: TRUE | AF57: FALSE | AG57: FALSE | AI57: 3500000 | AJ57: =AI57 -> 3500000 | AK57: Paid | AL57: Paid | AM57: Paid | AN57: Closed | AR57: FALSE | AS57: FALSE
B58: 45695 | C58: OS | D58: Hotel | F58: JIP | G58: TF | I58: Offering Beyond Travelindo Jakarta | J58: Corporate | K58: Mr Abu | N58: Entertainment | O58: Trekking | P58: 46 | Q58: Royal Tulip Gunung Geulis | R58: =if(ISBLANK($T58),"",$T58-$S58+1) -> 2 | S58: 45715 | T58: 45716 | U58: =if(W58="","", S58-V58 & " days") -> 20 days | V58: 45695 | W58: P046 | X58: Cancel | Y58: Cancel | AB58: TRUE | AC58: FALSE | AD58: FALSE | AE58: FALSE | AF58: FALSE | AG58: FALSE | AI58: 15417900 | AR58: FALSE | AS58: FALSE
B59: 45682 | C59: OS | D59: Repeater | F59: BR | G59: BR | I59: Daimler Truck - Cleaning Service | J59: Corporate | K59: Mr. Febri | L59: +62 813-2803-1899 | N59: Production | O59: ENT | P59: 1 | Q59: Cikarang - Bekasi | R59: =if(ISBLANK($T59),"",$T59-$S59+1) -> 1 | S59: 45716 | T59: 45716 | U59: =if(W59="","", S59-V59 & " days") -> 34 days | V59: 45682 | W59: P035 | X59: Signed & Deal | Y59: Confirm | AB59: FALSE | AC59: FALSE | AD59: FALSE | AE59: FALSE | AF59: FALSE | AG59: TRUE | AI59: 9823500 | AJ59: =AI59 -> 9823500 | AK59: Paid | AL59: Paid | AM59: Paid | AN59: Closed | AR59: FALSE | AS59: FALSE
B60: 45667 | C60: OS | D60: Direct | F60: JIP | G60: SB | I60: ICBC Indonesia | J60: Corporate | K60: Mr. Nixon | L60: +62 821-2708-2984 | N60: Employee Gathering | O60: RFT | P60: 15 | Q60: Syifa Adventure Rafting | R60: =if(ISBLANK($T60),"",$T60-$S60+1) -> 1 | S60: 45717 | T60: 45717 | U60: =if(W60="","", S60-V60 & " days") -> 50 days | V60: 45667 | W60: P017 | X60: Cancel | Y60: Cancel | AA60: No Response | AB60: TRUE | AC60: FALSE | AD60: FALSE | AE60: FALSE | AF60: FALSE | AG60: FALSE | AI60: 8325000 | AR60: FALSE | AS60: FALSE
B61: 45663 | C61: OS | D61: Repeater | F61: JIP | G61: BR | I61: PT Johnson Controls Indonesia | J61: Corporate | K61: Mrs. Selly Handayani | L61: +62 811-9603-998 | M61: selly.handayani@jci.com | N61: Employee Gathering | O61: Full Arrangement | P61: 160 | Q61: The Westin Jakarta | R61: =if(ISBLANK($T61),"",$T61-$S61+1) -> 1 | S61: 45729 | T61: 45729 | U61: =if(W61="","", S61-V61 & " days") -> 66 days | V61: 45663 | W61: P010 | X61: Signed & Deal | Y61: Confirm | AA61: - | AB61: TRUE | AC61: FALSE | AD61: FALSE | AE61: FALSE | AF61: FALSE | AG61: TRUE | AI61: 66760950 | AJ61: =AI61 -> 66760950 | AK61: Paid | AL61: Paid | AM61: Paid | AN61: Closed | AR61: TRUE | AS61: FALSE
B62: 45720 | C62: OS | D62: Repeater | F62: JIP | G62: OME | I62: Mrs Putri (TRAKNUS) | J62: Other | K62: Mrs. Putri | L62: +62 813-1590-8797 | N62: Production | O62: Production | R62: =if(ISBLANK($T62),"",$T62-$S62+1) -> 2 | S62: 45738 | T62: 45739 | U62: =if(W62="","", S62-V62 & " days") -> 18 days | V62: 45720 | W62: P072 | X62: Cancel | Y62: Cancel | AB62: FALSE | AC62: FALSE | AD62: FALSE | AE62: FALSE | AF62: FALSE | AG62: FALSE | AI62: 78800000 | AR62: FALSE | AS62: FALSE
B63: 45715 | C63: LS | D63: Repeater | F63: JIP | G63: SB | I63: Telkom Property | J63: Goverment | K63: Mrs. Farha Dina | L63: +62 813-1905-9828 | N63: Production | O63: Production | P63: 400 | Q63: Office Telkom Property | R63: =if(ISBLANK($T63),"",$T63-$S63+1) -> 2 | S63: 45740 | T63: 45741 | U63: =if(W63="","", S63-V63 & " days") -> 23 days | V63: 45717 | W63: P071 | X63: Signed & Deal | Y63: Confirm | AB63: TRUE | AC63: TRUE | AD63: TRUE | AE63: TRUE | AF63: FALSE | AG63: FALSE | AI63: 14552000 | AJ63: =AI63 -> 14552000 | AK63: Paid | AL63: Paid | AM63: Paid | AN63: Closed | AR63: FALSE | AS63: FALSE
B64: 45650 | C64: OS | D64: Partner | E64: Dhewa | F64: SYS | G64: MWB | I64: Koplove | J64: Other | K64: Dhewa | N64: Sport Event | O64: Production | P64: 1000 | Q64: Sirkuit Sentul | R64: =if(ISBLANK($T64),"",$T64-$S64+1) -> 1 | S64: 45748 | T64: 45748 | U64: =if(W64="","", S64-V64 & " days") -> 98 days | V64: 45650 | W64: P002 | X64: Cancel | Y64: Cancel | AA64: - | AB64: TRUE | AC64: FALSE | AD64: FALSE | AE64: FALSE | AF64: FALSE | AG64: FALSE | AI64: 324874050 | AR64: FALSE | AS64: FALSE
B65: 45755 | C65: LS | D65: Hotel | E65: Opick | F65: JIP | G65: SB | I65: Fak Hukum Univ Pakuan | J65: Other | N65: Other | O65: FG | P65: 35 | Q65: Lenirra Villa & Resto | R65: =if(ISBLANK($T65),"",$T65-$S65+1) -> 1 | S65: 45756 | T65: 45756 | U65: =if(W65="","", S65-V65 & " days") -> 1 days | V65: 45755 | W65: P077 | X65: Signed & Deal | Y65: Confirm | AB65: TRUE | AC65: TRUE | AD65: TRUE | AE65: TRUE | AF65: FALSE | AG65: FALSE | AI65: 3500000 | AJ65: =AI65 -> 3500000 | AK65: Paid | AL65: Paid | AM65: Paid | AN65: Closed | AR65: FALSE | AS65: FALSE
B66: 45682 | C66: OS | D66: Direct | F66: BR | G66: BR | I66: PT Arvia Pratama Tiara | J66: Corporate | K66: Mrs. Andhi Briliana | L66: +62 812-9764-5599 | N66: Employee Gathering | O66: OFR | P66: 400 | Q66: Bandung | R66: =if(ISBLANK($T66),"",$T66-$S66+1) -> 3 | S66: 45757 | T66: 45759 | U66: =if(W66="","", S66-V66 & " days") -> 75 days | V66: 45682 | W66: P034 | X66: Cancel | Y66: Cancel | AB66: FALSE | AC66: FALSE | AD66: FALSE | AE66: FALSE | AF66: FALSE | AG66: FALSE | AI66: 1354220415 | AR66: FALSE | AS66: FALSE
B67: 45756 | C67: OS | D67: Repeater | F67: JIP | G67: BR | I67: Gathering JCI with HAEI | J67: Corporate | K67: Lia Audina | L67: +62 851-5956-7767 | M67: lia.audina@jci.com | N67: Employee Gathering | O67: Full Arrangement | P67: 100 | Q67: Double Tree by Hilton Jakarta | R67: =if(ISBLANK($T67),"",$T67-$S67+1) -> 1 | S67: 45762 | T67: 45762 | U67: =if(W67="","", S67-V67 & " days") -> 20 days | V67: 45742 | W67: P078 | X67: Signed & Deal | Y67: Confirm | AB67: TRUE | AC67: TRUE | AD67: TRUE | AE67: TRUE | AF67: TRUE | AG67: FALSE | AI67: 99800100 | AJ67: =AI67 -> 99800100 | AK67: Paid | AL67: Paid | AM67: Paid | AN67: Closed | AR67: TRUE | AS67: FALSE
B68: 45680 | C68: OS | D68: Direct | F68: SYS | G68: SYS | I68: PT Wiralab Analitikal | J68: Corporate | K68: Mrs. Anne | L68: +62 856 9112 3843 | N68: Tour | O68: Full Arrangement | P68: 70 | Q68: Thailand | R68: =if(ISBLANK($T68),"",$T68-$S68+1) -> 3 | S68: 45764 | T68: 45766 | U68: =if(W68="","", S68-V68 & " days") -> 84 days | V68: 45680 | W68: P051 | X68: Cancel | Y68: Cancel | AA68: Competitor | AB68: TRUE | AC68: TRUE | AD68: FALSE | AE68: FALSE | AF68: FALSE | AG68: FALSE | AI68: 621600000 | AR68: FALSE | AS68: FALSE
B69: 45756 | C69: OS | D69: Repeater | F69: BR | G69: BR | I69: Costumer Gathering Button Scarves | J69: Corporate | K69: Shafa Yuandina | L69: +62 877-7176-8187 | N69: Employee Gathering | O69: Full Arrangement | P69: 100 | Q69: Bogor | R69: =if(ISBLANK($T69),"",$T69-$S69+1) -> 1 | S69: 45764 | T69: 45764 | U69: =if(W69="","", S69-V69 & " days") -> 8 days | V69: 45756 | W69: P079 | X69: Cancel | Y69: Cancel | AB69: FALSE | AC69: FALSE | AD69: FALSE | AE69: FALSE | AF69: FALSE | AG69: FALSE | AR69: FALSE | AS69: FALSE
B70: 45728 | C70: LS | D70: Repeater | F70: SBK | G70: SB | I70: Tazkia Tour & Travel | J70: Corporate | K70: Mr Fajar | L70: +62 817-4130-393 | N70: Other | O70: FG | P70: 220 | Q70: Pesona Alam resort & Spa | R70: =if(ISBLANK($T70),"",$T70-$S70+1) -> 1 | S70: 45767 | T70: 45767 | U70: =if(W70="","", S70-V70 & " days") -> 39 days | V70: 45728 | W70: P076 | X70: Signed & Deal | Y70: Confirm | AB70: FALSE | AC70: FALSE | AD70: FALSE | AE70: FALSE | AF70: FALSE | AG70: FALSE | AI70: 29000000 | AJ70: =AI70 -> 29000000 | AK70: Paid | AL70: Paid | AM70: Paid | AN70: Closed | AR70: TRUE | AS70: FALSE
B71: 45758 | C71: OS | D71: Repeater | F71: JIP | G71: OME | I71: Zurich | J71: Corporate | K71: Mellyana | N71: Employee Gathering | O71: TB - Scavenger Hunt | P71: 66 | Q71: TMII | R71: =if(ISBLANK($T71),"",$T71-$S71+1) | S71: 45767 | U71: =if(W71="","", S71-V71 & " days") -> 6 days | V71: 45761 | W71: P084 | X71: Cancel | Y71: Cancel | AA71: Competitor | AB71: FALSE | AC71: FALSE | AD71: FALSE | AE71: FALSE | AF71: FALSE | AG71: FALSE | AI71: 34632000 | AR71: FALSE | AS71: FALSE
B72: 45722 | C72: LS | D72: Hotel | E72: Zia | F72: JIP | G72: SB | I72: Mrs Zia | J72: Other | K72: Mrs Zia | L72: +62 822-3264-7697 | N72: Production | O72: Production | Q72: Pesona Alam resort & Spa | R72: =if(ISBLANK($T72),"",$T72-$S72+1) -> 3 | S72: 45768 | T72: 45770 | U72: =if(W72="","", S72-V72 & " days") -> 46 days | V72: 45722 | W72: P074 | X72: Cancel | Y72: Cancel | AA72: No Response | AB72: FALSE | AC72: FALSE | AD72: FALSE | AE72: FALSE | AF72: FALSE | AG72: FALSE | AI72: 42350000 | AR72: FALSE | AS72: FALSE
B73: 45766 | C73: OS | D73: Repeater | F73: JIP | G73: BR | I73: RDP DPR - Kemenpar | J73: Goverment | K73: Pradipta | L73: +62 857-1501-7046 | N73: Meeting | O73: Production | P73: 125 | Q73: Le Meridien Jakarta | R73: =if(ISBLANK($T73),"",$T73-$S73+1) -> 2 | S73: 45769 | T73: 45770 | U73: =if(W73="","", S73-V73 & " days") -> 2 days | V73: 45767 | W73: P086 | X73: Signed & Deal | Y73: Confirm | Z73: Offering Letter | AB73: FALSE | AC73: FALSE | AD73: FALSE | AE73: FALSE | AF73: FALSE | AG73: FALSE | AR73: FALSE | AS73: FALSE
B74: 45772 | C74: OS | D74: Repeater | F74: BR | G74: BR | I74: Daimler Tuck - Halal Bihalal | J74: Corporate | K74: Mrs. Yessi | L74: +62 813-2717-0256 | N74: Other | O74: Others | Q74: Daimler Truck Plan | R74: =if(ISBLANK($T74),"",$T74-$S74+1) -> 1 | S74: 45776 | T74: 45776 | U74: =if(W74="","", S74-V74 & " days") -> 4 days | V74: 45772 | W74: P088 | X74: Signed & Deal | Y74: Confirm | AB74: FALSE | AC74: FALSE | AD74: FALSE | AE74: FALSE | AF74: FALSE | AG74: FALSE | AI74: 43354300 | AJ74: =AI74 -> 43354300 | AK74: Paid | AL74: Paid | AM74: Paid | AN74: Closed | AR74: FALSE | AS74: FALSE
B75: 45776 | C75: OS | D75: Hotel | F75: JIP | G75: SB | I75: PT Gitaswara Indonesia | K75: Mrs Wanty | L75: +62 811 680 010 | N75: Other | O75: Trekking | P75: 10 | Q75: Royal Tulip / Lewi Hejo | R75: =if(ISBLANK($T75),"",$T75-$S75+1) -> 1 | S75: 45783 | T75: 45783 | U75: =if(W75="","", S75-V75 & " days") -> 7 days | V75: 45776 | W75: P090 | X75: Signed & Deal | Y75: Confirm | AB75: TRUE | AC75: TRUE | AD75: TRUE | AE75: TRUE | AF75: TRUE | AG75: FALSE | AI75: 7492500 | AJ75: =AI75 -> 7492500 | AK75: Paid | AL75: Paid | AM75: Paid | AN75: Closed | AR75: TRUE | AS75: FALSE
B76: 45794 | C76: OS | D76: Hotel | E76: The Alana Sentul | F76: JIP | G76: BR | I76: MKKS SD Kota Depok | J76: Goverment | N76: Meeting | O76: Full Arrangement | P76: 150 | Q76: The Alana Hotel Sentul | R76: =if(ISBLANK($T76),"",$T76-$S76+1) -> 2 | S76: 45787 | T76: 45788 | U76: =if(W76="","", S76-V76 & " days") -> -17 days | V76: 45804 | W76: P096 | X76: Cancel | Y76: Cancel | AA76: Budget | AB76: FALSE | AC76: FALSE | AD76: FALSE | AE76: FALSE | AF76: FALSE | AG76: FALSE | AI76: 487256000 | AR76: FALSE | AS76: FALSE
B77: 45712 | C77: OS | D77: Hotel | F77: JIP | G77: TF | I77: Nutrifood | J77: Corporate | K77: Mrs. Yasmin | N77: Employee Gathering | O77: TB | P77: 25 | Q77: Royal Tulip | R77: =if(ISBLANK($T77),"",$T77-$S77+1) -> 1 | S77: 45789 | T77: 45789 | U77: =if(W77="","", S77-V77 & " days") -> 77 days | V77: 45712 | W77: P066 | X77: Cancel | Y77: Cancel | AA77: No Response | AB77: TRUE | AC77: TRUE | AD77: FALSE | AE77: FALSE | AF77: FALSE | AG77: FALSE | AI77: 13181250 | AR77: FALSE | AS77: FALSE
B78: 45791 | C78: OS | D78: Repeater | F78: JIP | G78: TF | I78: OJK | J78: Goverment | K78: Mrs. Andry Triayuwerdhaty | L78: +62 813-8613-1594 | N78: Employee Gathering | O78: OFR | P78: 70 | Q78: Alana Sentul | R78: =if(ISBLANK($T78),"",$T78-$S78+1) -> 30 | S78: 45791 | T78: 45820 | U78: =if(W78="","", S78-V78 & " days") -> -29 days | V78: 45820 | W78: P092 | X78: Cancel | Y78: Cancel | AB78: TRUE | AC78: FALSE | AD78: FALSE | AE78: FALSE | AF78: FALSE | AG78: FALSE | AI78: 52170000 | AR78: FALSE | AS78: FALSE
B79: 45696 | C79: OS | D79: Hotel | F79: JIP | G79: TF | I79: PAPDI Bekasi | J79: Other | K79: Dr. Irma | L79: +62 859 2066 0026 | N79: Production | O79: Production | Q79: Harris Bekasi | R79: =if(ISBLANK($T79),"",$T79-$S79+1) -> 2 | S79: 45794 | T79: 45795 | U79: =if(W79="","", S79-V79 & " days") -> 98 days | V79: 45696 | W79: P048 | X79: Cancel | Y79: Cancel | AB79: TRUE | AC79: FALSE | AD79: FALSE | AE79: FALSE | AF79: FALSE | AG79: FALSE | AI79: 48951000 | AR79: FALSE | AS79: FALSE
B80: 45711 | C80: OS | D80: Repeater | F80: JIP | G80: TF | I80: Sekolah Lentera Indonesia | J80: Student | K80: Mrs. Anty | L80: +62 858-9464-2061 | N80: Employee Gathering | O80: TB | P80: 50 | Q80: Highland Park | R80: =if(ISBLANK($T80),"",$T80-$S80+1) -> 2 | S80: 45796 | T80: 45797 | U80: =if(W80="","", S80-V80 & " days") -> 85 days | V80: 45711 | W80: P065 | X80: Signed & Deal | Y80: Confirm | AB80: TRUE | AC80: TRUE | AD80: TRUE | AE80: TRUE | AF80: FALSE | AG80: TRUE | AI80: 29400000 | AJ80: =AI80 -> 29400000 | AK80: Paid | AL80: Paid | AM80: Paid | AN80: Closed | AR80: TRUE | AS80: FALSE
B81: 45775 | C81: OS | D81: Partner | E81: Ipung | F81: JIP | G81: SB | I81: Aeon Fantasy Indonesia | J81: Corporate | K81: Mrs Ovie | N81: Production | O81: Others | P81: 130 | Q81: Jambuluwuk Jakarta | R81: =if(ISBLANK($T81),"",$T81-$S81+1) -> 1 | S81: 45796 | T81: 45796 | U81: =if(W81="","", S81-V81 & " days") -> 20 days | V81: 45776 | W81: P089 | X81: Signed & Deal | Y81: Confirm | AB81: TRUE | AC81: TRUE | AD81: TRUE | AE81: TRUE | AF81: TRUE | AG81: FALSE | AI81: 76000000 | AJ81: =AI81 -> 76000000 | AK81: Paid | AL81: Paid | AM81: Paid | AN81: Closed | AR81: TRUE | AS81: FALSE
B82: 45786 | C82: OS | D82: Hotel | E82: Nova (Royal Tulip) | F82: JIP | G82: OME | I82: PDAM Bandung | J82: Corporate | K82: Mrs Susan | L82: +62 812 2197 7627 | N82: Employee Gathering | O82: Trekking | P82: 35 | Q82: The Alana Hotel/Leuwi Hejo | R82: =if(ISBLANK($T82),"",$T82-$S82+1) -> 1 | S82: 45800 | T82: 45800 | U82: =if(W82="","", S82-V82 & " days") -> 14 days | V82: 45786 | W82: P093 | X82: Signed & Deal | Y82: Confirm | AB82: TRUE | AC82: TRUE | AD82: TRUE | AE82: TRUE | AF82: TRUE | AG82: FALSE | AI82: 16844250 | AJ82: =AI82 -> 16844250 | AK82: Paid | AL82: Paid | AM82: Paid | AN82: Closed | AO82: https://drive.google.com/drive/folders/1Z06kZmc1B3WUjgMAdNPrtePth25Xwapv?usp=sharing | AR82: TRUE | AS82: FALSE
B83: 45755 | C83: OS | D83: Direct | F83: SYS | G83: BR | I83: PT Menarini Indria laboratories | J83: Corporate | K83: Ardi Utomo | L83: +62 812-9595-8567 | N83: Employee Gathering | O83: Full Arrangement | P83: 100 | Q83: Jogja | R83: =if(ISBLANK($T83),"",$T83-$S83+1) | S83: 45802 | U83: =if(W83="","", S83-V83 & " days") -> 44 days | V83: 45758 | W83: P082 | X83: Cancel | Y83: Cancel | AA83: Competitor | AB83: FALSE | AC83: FALSE | AD83: FALSE | AE83: FALSE | AF83: FALSE | AG83: FALSE | AR83: FALSE | AS83: FALSE
B84: 45784 | C84: LS | D84: Web | F84: MWB | G84: OME | I84: PT Acaraki Nusantara Persada | J84: Corporate | K84: Mrs. Ayu | L84: +62 821 8107 6432 | N84: Employee Gathering | O84: Full Arrangement | P84: 55 | Q84: Bogor | R84: =if(ISBLANK($T84),"",$T84-$S84+1) -> 2 | S84: 45805 | T84: 45806 | U84: =if(W84="","", S84-V84 & " days") -> 21 days | V84: 45784 | W84: P119 | X84: Signed & Deal | Y84: Confirm | AB84: TRUE | AC84: TRUE | AD84: TRUE | AE84: TRUE | AF84: FALSE | AG84: FALSE | AI84: 52485000 | AJ84: =AI84 -> 52485000 | AK84: Paid | AL84: Paid | AM84: Paid | AN84: Closed | AO84: https://drive.google.com/drive/folders/1t5rRSFqMQDaSNhDYh2kzZPDLYJDSfx-Z?usp=sharing
B85: 45799 | C85: LS | D85: Hotel | E85: Mrs. Dewi Purnama - PARS | F85: JIP | G85: BR | I85: Asuransi Sinar Mas | J85: Corporate | K85: Mrs. Christianty | L85: +62 815-8860-334 | M85: Christianty_Wijaya@Sinarmas.co.id | N85: Family Gathering | O85: Full Arrangement | P85: 706 | Q85: Pesona Alam resort & Spa - The Botanica | R85: =if(ISBLANK($T85),"",$T85-$S85+1) -> 3 | S85: 45805 | T85: 45807 | U85: =if(W85="","", S85-V85 & " days") -> 6 days | V85: 45799 | W85: P097 | X85: Signed & Deal | Y85: Confirm | AB85: TRUE | AC85: TRUE | AD85: TRUE | AE85: TRUE | AF85: TRUE | AG85: TRUE | AI85: 2048362560 | AJ85: =AI85 -> 2048362560 | AK85: Paid | AL85: Paid | AM85: Paid | AN85: Closed | AO85: https://drive.google.com/drive/folders/1sYmR7MLtVQ40-Pu9Q91F0ZtDJEJMqj8D | AP85: https://drive.google.com/drive/folders/15C2dnAsFjsForf2zNng0SqYJBdM1XUKV | AR85: TRUE | AS85: FALSE
B86: 45714 | C86: OS | D86: Direct | F86: SYS | G86: SYS | I86: Lazada | J86: Corporate | K86: Jumi | N86: Employee Gathering | O86: Full Arrangement | P86: 60 | Q86: Bali / Pulau Seribu | R86: =if(ISBLANK($T86),"",$T86-$S86+1) | S86: 45809 | U86: =if(W86="","", S86-V86 & " days") -> 95 days | V86: 45714 | W86: P081 | X86: Cancel | Y86: Cancel | AB86: FALSE | AC86: FALSE | AD86: FALSE | AE86: FALSE | AF86: FALSE | AG86: FALSE | AR86: FALSE | AS86: FALSE
B87: 45741 | C87: LS | D87: Direct | F87: SYS | G87: SYS | I87: Yayasan Syiar Bangsa (Summarecon Group) | J87: Other | N87: Production | O87: Production | P87: 120 | Q87: Anyer | R87: =if(ISBLANK($T87),"",$T87-$S87+1) | S87: 45809 | U87: =if(W87="","", S87-V87 & " days") -> 52 days | V87: 45757 | W87: P083 | X87: Cancel | Y87: Cancel | AB87: FALSE | AC87: FALSE | AD87: FALSE | AE87: FALSE | AF87: FALSE | AG87: FALSE | AR87: FALSE | AS87: FALSE
B88: 45772 | C88: OS | D88: Hotel | F88: JIP | G88: SB | I88: Bank Mandiri | J88: Goverment | N88: Employee Gathering | O88: Others | P88: 50 | Q88: Royal Tulip Gn. Geulis | R88: =if(ISBLANK($T88),"",$T88-$S88+1) -> 2 | S88: 45809 | T88: 45810 | U88: =if(W88="","", S88-V88 & " days") -> 36 days | V88: 45773 | W88: P087 | X88: Cancel | Y88: Cancel | AA88: Postponed | AB88: FALSE | AC88: FALSE | AD88: FALSE | AE88: FALSE | AF88: FALSE | AG88: FALSE | AR88: FALSE | AS88: FALSE
B89: 45701 | C89: OS | D89: Repeater | F89: BR | G89: BR | I89: Aminef | J89: Corporate | K89: Mrs. Rianti | L89: +62 811-9768-900 | N89: Other | O89: TB - Scavenger Hunt | P89: 22 | Q89: Kebun Raya Bogor | R89: =if(ISBLANK($T89),"",$T89-$S89+1) -> 1 | S89: 45812 | T89: 45812 | U89: =if(W89="","", S89-V89 & " days") -> 51 days | V89: 45761 | W89: P056 | X89: Cancel | Y89: Cancel | AB89: FALSE | AC89: FALSE | AD89: FALSE | AE89: FALSE | AF89: FALSE | AG89: FALSE | AI89: 31283241 | AR89: FALSE | AS89: FALSE
B90: 45703 | C90: OS | D90: Web | F90: UT | G90: UT | I90: PT SHN | J90: Corporate | K90: Mrs. Isabela | L90: +62 895 3858 72327 | N90: Employee Gathering | O90: TB | P90: 80 | Q90: Villa | R90: =if(ISBLANK($T90),"",$T90-$S90+1) -> 1 | S90: 45815 | T90: 45815 | U90: =if(W90="","", S90-V90 & " days") -> 112 days | V90: 45703 | W90: P064 | X90: Cancel | Y90: Cancel | AB90: FALSE | AC90: FALSE | AD90: FALSE | AE90: FALSE | AF90: FALSE | AG90: FALSE | AI90: 35298000 | AR90: FALSE | AS90: FALSE
B91: 45793 | C91: OS | D91: Direct | F91: JIP | G91: UT | I91: Vencedor Travel Bandung | J91: Corporate | K91: Mrs. Elsa | N91: Employee Gathering | O91: RFT | P91: 30 | Q91: Area Rafting | R91: =if(ISBLANK($T91),"",$T91-$S91+1) -> 2 | S91: 45815 | T91: 45816 | U91: =if(W91="","", S91-V91 & " days") -> 22 days | V91: 45793 | W91: P109 | X91: Cancel | Y91: Cancel | AB91: FALSE | AC91: FALSE | AD91: FALSE | AE91: FALSE | AF91: FALSE | AG91: FALSE | AR91: FALSE | AS91: FALSE
B92: 45815 | C92: LS | D92: Hotel | E92: Opick | F92: SBK | G92: SB | I92: PT Energia | J92: Corporate | K92: Mr Fauzan | L92: +62 858 8292 3693 | N92: Production | O92: Production | P92: 1 | Q92: Lenirra Villa & Resto | R92: =if(ISBLANK($T92),"",$T92-$S92+1) -> 1 | S92: 45821 | T92: 45821 | U92: =if(W92="","", S92-V92 & " days") -> 3 days | V92: 45818 | W92: P170 | X92: Signed & Deal | Y92: Confirm | AB92: TRUE | AC92: TRUE | AD92: TRUE | AE92: TRUE | AF92: TRUE | AG92: FALSE | AI92: 3500000 | AJ92: =AI92 -> 3500000 | AK92: Paid | AL92: Paid | AM92: Paid | AN92: Closed | AR92: FALSE | AS92: FALSE
B93: 45819 | C93: LS | D93: Hotel | E93: Kang Opick | F93: JIP | G93: SB | I93: PT Energia | J93: Corporate | K93: Mr Fauzan | L93: +62 858 8292 3693 | N93: Production | O93: Production | Q93: Lenirra Villa & Resto | R93: =if(ISBLANK($T93),"",$T93-$S93+1) -> 1 | S93: 45821 | T93: 45821 | U93: =if(W93="","", S93-V93 & " days") -> 2 days | V93: 45819 | W93: P104 | X93: Signed & Deal | Y93: Confirm | AB93: TRUE | AC93: FALSE | AD93: TRUE | AE93: TRUE | AF93: FALSE | AG93: FALSE | AI93: 3500000 | AJ93: =AI93 -> 3500000 | AK93: Paid | AL93: Paid | AM93: Paid | AN93: Closed | AR93: FALSE | AS93: FALSE
B94: 45778 | C94: OS | D94: Hotel | E94: Novalita (Royal Tulip) | F94: JIP | G94: OME | I94: Kejaksaan | J94: Other | K94: Mrs Sri Muntari | L94: +62 813 1911 6664 | N94: Other | O94: FG | P94: 80 | Q94: Royal Tulip | R94: =if(ISBLANK($T94),"",$T94-$S94+1) -> 1 | S94: 45822 | T94: 45822 | U94: =if(W94="","", S94-V94 & " days") -> 44 days | V94: 45778 | W94: P094 | X94: Signed & Deal | Y94: Confirm | AB94: TRUE | AC94: TRUE | AD94: TRUE | AE94: TRUE | AF94: FALSE | AG94: FALSE | AI94: 29670000 | AJ94: =AI94 -> 29670000 | AK94: Paid | AL94: Paid | AM94: Paid | AN94: Closed | AR94: FALSE | AS94: FALSE
B95: 45819 | C95: OS | D95: Hotel | E95: Novalita (Royal Tulip) | F95: JIP | G95: OME | I95: Kejaksaan | J95: Other | K95: Mrs Sri Muntari | L95: +62 857-7433-7749 | N95: Other | O95: Production | Q95: Royal Tulip | R95: =if(ISBLANK($T95),"",$T95-$S95+1) -> 1 | S95: 45822 | T95: 45822 | U95: =if(W95="","", S95-V95 & " days") -> 3 days | V95: 45819 | W95: P103 | X95: Signed & Deal | Y95: Confirm | AB95: TRUE | AC95: TRUE | AD95: TRUE | AE95: FALSE | AF95: FALSE | AG95: FALSE | AI95: 3800000 | AJ95: =AI95 -> 3800000 | AK95: Paid | AL95: Paid | AM95: Paid | AN95: Closed | AR95: FALSE | AS95: FALSE
B96: 45797 | C96: LS | D96: Hotel | E96: Dandy Perwansyah | F96: JIP | G96: OME | I96: D'Sawah (Al Azhar) | J96: Other | K96: Mrs Siti Ayanti | L96: +62 857-7433-7749 | N96: Employee Gathering | O96: FG | P96: 114 | Q96: D'Sawah | R96: =if(ISBLANK($T96),"",$T96-$S96+1) -> 1 | S96: 45823 | T96: 45823 | U96: =if(W96="","", S96-V96 & " days") -> 26 days | V96: 45797 | W96: P095 | X96: Signed & Deal | Y96: Confirm | AB96: TRUE | AC96: TRUE | AD96: TRUE | AE96: FALSE | AF96: FALSE | AG96: FALSE | AI96: 11070000 | AK96: Paid | AL96: Paid | AM96: Paid | AN96: Closed | AR96: TRUE | AS96: FALSE
B97: 45805 | C97: OS | D97: Repeater | F97: JIP | G97: BR | I97: Virgo Ramayana Music & Entertainment | J97: Corporate | K97: Mr. Muhamad Hambali | N97: Employee Gathering | O97: Full Arrangement | P97: 50 | Q97: Jogjakarta | R97: =if(ISBLANK($T97),"",$T97-$S97+1) -> 4 | S97: 45827 | T97: 45830 | U97: =if(W97="","", S97-V97 & " days") -> 22 days | V97: 45805 | W97: P098 | X97: Cancel | Y97: Cancel | AB97: FALSE | AC97: FALSE | AD97: FALSE | AE97: FALSE | AF97: FALSE | AG97: FALSE | AI97: 215811750 | AR97: FALSE | AS97: FALSE
B98: 45538 | C98: OS | D98: Hotel | F98: JIP | G98: OME | I98: SD Bakti Mulya 400 | J98: Student | K98: Mrs. Annys | N98: Other | O98: FG | P98: 60 | Q98: Royal Tulip Gn. Geulis | R98: =if(ISBLANK($T98),"",$T98-$S98+1) -> 1 | S98: 45829 | T98: 45829 | U98: =if(W98="","", S98-V98 & " days") -> 291 days | V98: 45538 | W98: P075 | X98: Signed & Deal | Y98: Confirm | AB98: FALSE | AC98: FALSE | AD98: FALSE | AE98: FALSE | AF98: FALSE | AG98: FALSE | AI98: 16500000 | AJ98: =AI98 -> 16500000 | AK98: Paid | AL98: Paid | AM98: Paid | AN98: Closed | AR98: TRUE | AS98: FALSE
B99: 45776 | C99: OS | D99: Hotel | E99: Jaka | F99: JIP | G99: BR | I99: NTT Data | J99: Corporate | K99: Mrs. Turi | N99: Employee Gathering | O99: TB | P99: 300 | Q99: Lido Lake Resort | R99: =if(ISBLANK($T99),"",$T99-$S99+1) -> 1 | S99: 45829 | T99: 45829 | U99: =if(W99="","", S99-V99 & " days") -> 23 days | V99: 45806 | W99: P091 | X99: Cancel | Y99: Cancel | AA99: Budget | AB99: FALSE | AC99: FALSE | AD99: TRUE | AE99: FALSE | AF99: TRUE | AG99: FALSE | AI99: 299615715 | AR99: FALSE | AS99: FALSE
B100: 45769 | C100: OS | D100: Repeater | F100: JIP | G100: OME | I100: Yamaha Music Indonesia | J100: Corporate | K100: Christina | L100: +62 822 6000 2921 | M100: christina.simanungkalit@music.yamaha.com | N100: Entertainment | O100: ENT | Q100: Yamaha Music Centre Building | R100: =if(ISBLANK($T100),"",$T100-$S100+1) | S100: 45834 | U100: =if(W100="","", S100-V100 & " days") -> 65 days | V100: 45769 | W100: P085 | X100: Cancel | Y100: Cancel | AA100: No Response | AB100: FALSE | AC100: FALSE | AD100: FALSE | AE100: FALSE | AF100: FALSE | AG100: FALSE | AI100: 9500000 | AR100: FALSE | AS100: FALSE
B101: 45817 | C101: OS | D101: Repeater | F101: BR | G101: BR | I101: Fakultas Kedokteran IPB | J101: Goverment | K101: Mrs. Rosita | L101: +62 821-4910-0499 | N101: Employee Gathering | O101: Full Arrangement | P101: 20 | Q101: Pulau Seribu | R101: =if(ISBLANK($T101),"",$T101-$S101+1) -> 3 | S101: 45835 | T101: 45837 | U101: =if(W101="","", S101-V101 & " days") -> 18 days | V101: 45817 | W101: P101 | X101: Cancel | Y101: Cancel | Z101: Change Destination | AB101: FALSE | AC101: FALSE | AD101: FALSE | AE101: FALSE | AF101: FALSE | AG101: FALSE | AI101: 62271000 | AR101: TRUE | AS101: FALSE
...

Sheet Helper
A1: Employee List | E1: Inquiry By | F1: Category Company | G1: Event Category | H1: Program
E2: Hotel | F2: Corporate | G2: Employee Gathering | H2: TB | J2: INQ By | K2: SUM of Budget (Rp) | M2: INQ By | N2: SUM of Budget (Rp) | P2: Event Date Start | Q2: COUNTA of Quotation Number | T2: Event Date End | U2: COUNTA of Quotation Number | W2: PO | X2: SUM of Budget (Rp) | AA2: Target Revenue 2025
E3: Repeater | F3: Goverment | G3: Family Gathering | H3: TB - Scavenger Hunt | J3: Direct | K3: 9899900392 | M3: Direct | N3: 9899900392 | P3: June-2025 | Q3: 1 | R3: {=XLOOKUP(P3,Workflow!$S$6:$S$270,Workflow!$W$6:$W$270)} -> P073 | T3: June-2025 | U3: 1 | V3: {=XLOOKUP(T3,Workflow!$T$6:$T$270,Workflow!$W$6:$W$270)} -> P073 | W3: AR | X3: 1538726557 | Y3: =K81/X3*100% -> 0.80684707 | AA3: Target 2025 | AB3: SUM of Target
E4: Partner | F4: Student | G4: Production | H4: FG | J4: Hotel | K4: 10976511799 | M4: Hotel | N4: 10976511799 | P4: 46067 | Q4: 1 | R4: {=XLOOKUP(P4,Workflow!$S$6:$S$270,Workflow!$W$6:$W$270)} -> P175 | T4: 46067 | U4: 1 | V4: {=XLOOKUP(T4,Workflow!$T$6:$T$270,Workflow!$W$6:$W$270)} -> P175 | W4: BR | X4: 5990341692 | Y4: =K82/X4*100% -> 0.16798411 | AA4: Mohammad Ramli | AB4: 3000000000
A5: Employee ID | B5: Employee Name | C5: Contact | E5: Direct | F5: Other | G5: Entertainment | H5: OFR | J5: Instagram | K5: 1562303761 | M5: Instagram | N5: 1562303761 | P5: 46042 | Q5: 1 | R5: {=XLOOKUP(P5,Workflow!$S$6:$S$270,Workflow!$W$6:$W$270)} -> P221 | T5: 46042 | U5: 1 | V5: {=XLOOKUP(T5,Workflow!$T$6:$T$270,Workflow!$W$6:$W$270)} -> P221 | W5: JC | X5: 226594000 | Y5: =K83/X5*100% -> 1 | AA5: Jaka Iklas Pratama | AB5: 3000000000
A6: 1001 | B6: JC | C6: +62 896 0113 1400 | E6: Instagram | F6: Campus | G6: Tour | H6: PB | J6: Partner | K6: 2698687930 | L6: =AVERAGE(K3:K8) -> 5252603314 | M6: Partner | N6: 2698687930 | P6: 46023 | Q6: 1 | R6: {=XLOOKUP(P6,Workflow!$S$6:$S$270,Workflow!$W$6:$W$270)} -> P244 | T6: 46023 | U6: 1 | V6: {=XLOOKUP(T6,Workflow!$T$6:$T$270,Workflow!$W$6:$W$270)} -> P244 | W6: JIP | X6: 15300327586 | Y6: =K84/X6*100% -> 0.40939534 | AA6: Ridho Abdullah | AB6: 2000000000
A7: 1002 | B7: MWB | C7: +62 821 1299 7371 | E7: Web | G7: Meeting | H7: RFT | J7: Repeater | K7: 6246172201 | M7: Repeater | N7: 6246172201 | P7: 46017 | Q7: 1 | R7: {=XLOOKUP(P7,Workflow!$S$6:$S$270,Workflow!$W$6:$W$270)} -> P247 | T7: 46019 | U7: 1 | V7: {=XLOOKUP(T7,Workflow!$T$6:$T$270,Workflow!$W$6:$W$270)} -> P247 | W7: MWB | X7: 1028064900 | Y7: =K85/X7*100% -> 0.051052224 | AA7: Syarah Syukrilah | AB7: 1000000000
A8: 1003 | B8: JIP | C8: +62 858 8882 8443 | E8: Other | G8: Other | H8: ARC | J8: Web | K8: 132043800 | M8: Web | N8: 132043800 | P8: 46014 | Q8: 1 | R8: {=XLOOKUP(P8,Workflow!$S$6:$S$270,Workflow!$W$6:$W$270)} -> P248 | T8: 46015 | U8: 1 | V8: {=XLOOKUP(T8,Workflow!$T$6:$T$270,Workflow!$W$6:$W$270)} -> P248 | W8: RA | X8: 37100000 | Y8: =K86/X8*100% -> 1 | AA8: Light Spirit | AB8: 1000000000
A9: 1004 | B9: DS | C9: +62 858 9020 6621 | G9: Sport Event | H9: Production | J9: Grand Total | K9: 31515619883 | M9: Grand Total | N9: 31515619883 | P9: 46013 | Q9: 1 | R9: {=XLOOKUP(P9,Workflow!$S$6:$S$270,Workflow!$W$6:$W$270)} -> P258 | T9: 46014 | U9: 1 | V9: {=XLOOKUP(T9,Workflow!$T$6:$T$270,Workflow!$W$6:$W$270)} -> P258 | W9: SBK | X9: 839618080 | Y9: =K87/X9*100% -> 0.84943309 | AA9: Arin Fitria | AB9: 800000000
A10: 1005 | B10: RA | C10: +62 811 1103 389 | H10: Tour | P10: 46010 | Q10: 2 | R10: {=XLOOKUP(P10,Workflow!$S$6:$S$270,Workflow!$W$6:$W$270)} -> P253 | T10: 46010 | U10: 2 | V10: {=XLOOKUP(T10,Workflow!$T$6:$T$270,Workflow!$W$6:$W$270)} -> P253 | W10: SR | X10: 1052502111 | Y10: =K88/X10*100% -> 0.60806269 | AA10: Taufan Hidayat | AB10: 500000000
A11: 1006 | B11: BR | C11: +62 857 8031 3089 | H11: ENT | J11: Program Status | K11: COUNTA of Quotation Number | P11: 46009 | Q11: 1 | R11: {=XLOOKUP(P11,Workflow!$S$6:$S$270,Workflow!$W$6:$W$270)} -> P245 | T11: 46009 | U11: 1 | V11: {=XLOOKUP(T11,Workflow!$T$6:$T$270,Workflow!$W$6:$W$270)} -> P245 | W11: SYS | X11: 4828612312 | Y11: =K89/X11*100% -> 0.025408878 | AA11: Putera Katresna | AB11: 500000000
A12: 1007 | B12: AR | C12: +62 858 1437 1788 | J12: Cancel | K12: 142 | P12: 46006 | Q12: 1 | R12: {=XLOOKUP(P12,Workflow!$S$6:$S$270,Workflow!$W$6:$W$270)} -> P256 | T12: 46006 | U12: 1 | V12: {=XLOOKUP(T12,Workflow!$T$6:$T$270,Workflow!$W$6:$W$270)} -> P256 | W12: TF | X12: 472622845 | Y12: =K90/X12*100% -> 0.57078473 | AA12: M.Syahrul Ramadhan | AB12: 200000000
A13: 1008 | B13: SYS | C13: +62 812 9730 9703 | J13: Confirm | K13: 122 | M13: PO | N13: COUNTA of Quotation Number | P13: 46004 | Q13: 1 | R13: {=XLOOKUP(P13,Workflow!$S$6:$S$270,Workflow!$W$6:$W$270)} -> P254 | T13: 46005 | U13: 1 | V13: {=XLOOKUP(T13,Workflow!$T$6:$T$270,Workflow!$W$6:$W$270)} -> P242 | W13: UT | X13: 201109800 | Y13: =0/X13*100% -> 0
A14: 1009 | B14: TF | C14: +62 896 5180 7061 | J14: Grand Total | K14: 264 | M14: AR | N14: 5 | P14: 46003 | Q14: 5 | R14: {=XLOOKUP(P14,Workflow!$S$6:$S$270,Workflow!$W$6:$W$270)} -> P230 | T14: 46004 | U14: 2 | V14: {=XLOOKUP(T14,Workflow!$T$6:$T$270,Workflow!$W$6:$W$270)} -> P249 | W14: Grand Total | X14: 31515619883 | Y14: =0/X14*100% -> 0
A15: 1010 | B15: SR | C15: +62 857 7407 3054 | M15: BR | N15: 31 | P15: 46002 | Q15: 1 | R15: {=XLOOKUP(P15,Workflow!$S$6:$S$270,Workflow!$W$6:$W$270)} -> P249 | T15: 46003 | U15: 3 | V15: {=XLOOKUP(T15,Workflow!$T$6:$T$270,Workflow!$W$6:$W$270)} -> P230
A16: 1011 | B16: UT | C16: +62 821 1191 0614 | M16: JC | N16: 1 | P16: 46000 | Q16: 1 | R16: {=XLOOKUP(P16,Workflow!$S$6:$S$270,Workflow!$W$6:$W$270)} -> P255 | T16: 46001 | U16: 1 | V16: {=XLOOKUP(T16,Workflow!$T$6:$T$270,Workflow!$W$6:$W$270)} -> P234
A17: 1012 | B17: SBK | C17: +62 812 9749 9543 | M17: JIP | N17: 181 | P17: 45999 | Q17: 2 | R17: {=XLOOKUP(P17,Workflow!$S$6:$S$270,Workflow!$W$6:$W$270)} -> P224 | T17: 46000 | U17: 1 | V17: {=XLOOKUP(T17,Workflow!$T$6:$T$270,Workflow!$W$6:$W$270)} -> P255
A18: 1013 | B18: OME | C18: +62 822 4961 6181 | M18: MWB | N18: 3 | P18: 45996 | Q18: 3 | R18: {=XLOOKUP(P18,Workflow!$S$6:$S$270,Workflow!$W$6:$W$270)} -> P219 | T18: 45999 | U18: 1 | V18: {=XLOOKUP(T18,Workflow!$T$6:$T$270,Workflow!$W$6:$W$270)} -> P224
M19: RA | N19: 1 | P19: 45994 | Q19: 2 | R19: {=XLOOKUP(P19,Workflow!$S$6:$S$270,Workflow!$W$6:$W$270)} -> P176 | T19: 45996 | U19: 3 | V19: {=XLOOKUP(T19,Workflow!$T$6:$T$270,Workflow!$W$6:$W$270)} -> P219 | Y19: =K81/X19*100% -> 1.5518963
E20: =L70/L71*100% -> 0.3355004 | M20: SBK | N20: 11 | P20: 45992 | Q20: 2 | R20: {=XLOOKUP(P20,Workflow!$S$6:$S$270,Workflow!$W$6:$W$270)} -> P204 | T20: 45995 | U20: 1 | V20: {=XLOOKUP(T20,Workflow!$T$6:$T$270,Workflow!$W$6:$W$270)} -> P176 | Y20: =K84/X20*100% -> 2.0879609
E21: =K46/K47*100% -> 0.46212121 | M21: SR | N21: 5 | P21: 45990 | Q21: 2 | R21: {=XLOOKUP(P21,Workflow!$S$6:$S$270,Workflow!$W$6:$W$270)} -> P220 | T21: 45994 | U21: 1 | V21: {=XLOOKUP(T21,Workflow!$T$6:$T$270,Workflow!$W$6:$W$270)} -> P251 | Y21: =K87/X21*100% -> 0.71319938
M22: SYS | N22: 19 | P22: 45989 | Q22: 3 | R22: {=XLOOKUP(P22,Workflow!$S$6:$S$270,Workflow!$W$6:$W$270)} -> P215 | T22: 45993 | U22: 1 | V22: {=XLOOKUP(T22,Workflow!$T$6:$T$270,Workflow!$W$6:$W$270)} -> P246 | Y22: =K88/X22*100% -> 3.1999363
J23: Payment Status | K23: COUNTA of Quotation Number | M23: TF | N23: 3 | P23: 45988 | Q23: 2 | R23: {=XLOOKUP(P23,Workflow!$S$6:$S$270,Workflow!$W$6:$W$270)} -> P134 | T23: 45992 | U23: 1 | V23: {=XLOOKUP(T23,Workflow!$T$6:$T$270,Workflow!$W$6:$W$270)} -> P204 | Y23: =K82/X23*100% -> 0.33542741
J24: Invoice Sent | K24: 1 | M24: UT | N24: 4 | P24: 45987 | Q24: 1 | R24: {=XLOOKUP(P24,Workflow!$S$6:$S$270,Workflow!$W$6:$W$270)} -> P259 | T24: 45991 | U24: 3 | V24: {=XLOOKUP(T24,Workflow!$T$6:$T$270,Workflow!$W$6:$W$270)} -> P215 | Y24: =0/X24*100% -> 0
J25: Out Standing | K25: 12 | M25: Grand Total | N25: 264 | P25: 45986 | Q25: 1 | R25: {=XLOOKUP(P25,Workflow!$S$6:$S$270,Workflow!$W$6:$W$270)} -> P127 | T25: 45990 | U25: 1 | V25: {=XLOOKUP(T25,Workflow!$T$6:$T$270,Workflow!$W$6:$W$270)} -> P220 | Y25: =K86/X25*100% -> 0.01855
J26: Paid | K26: 103 | P26: 45983 | Q26: 3 | R26: {=XLOOKUP(P26,Workflow!$S$6:$S$270,Workflow!$W$6:$W$270)} -> P212 | T26: 45989 | U26: 1 | V26: {=XLOOKUP(T26,Workflow!$T$6:$T$270,Workflow!$W$6:$W$270)} -> P239 | Y26: =K89/X26*100% -> 0.12268962
J27: Grand Total | K27: 116 | M27: Cancel Reason | N27: COUNTA of Quotation Number | P27: 45982 | Q27: 5 | R27: {=XLOOKUP(P27,Workflow!$S$6:$S$270,Workflow!$W$6:$W$270)} -> P185 | T27: 45988 | U27: 2 | V27: {=XLOOKUP(T27,Workflow!$T$6:$T$270,Workflow!$W$6:$W$270)} -> P134 | Y27: =K90/X27*100% -> 0.53953181
N28: 181 | P28: 45980 | Q28: 1 | R28: {=XLOOKUP(P28,Workflow!$S$6:$S$270,Workflow!$W$6:$W$270)} -> P207 | T28: 45987 | U28: 1 | V28: {=XLOOKUP(T28,Workflow!$T$6:$T$270,Workflow!$W$6:$W$270)} -> P259 | Y28: =K89/X28*100% -> 0.010224135
M29: - | N29: 37 | P29: 45975 | Q29: 2 | R29: {=XLOOKUP(P29,Workflow!$S$6:$S$270,Workflow!$W$6:$W$270)} -> P227 | T29: 45986 | U29: 1 | V29: {=XLOOKUP(T29,Workflow!$T$6:$T$270,Workflow!$W$6:$W$270)} -> P127
M30: Budget | N30: 5 | P30: 45974 | Q30: 1 | R30: {=XLOOKUP(P30,Workflow!$S$6:$S$270,Workflow!$W$6:$W$270)} -> P180 | T30: 45983 | U30: 3 | V30: {=XLOOKUP(T30,Workflow!$T$6:$T$270,Workflow!$W$6:$W$270)} -> P212
J31: PM | K31: Task ID | M31: Competitor | N31: 12 | P31: 45972 | Q31: 1 | R31: {=XLOOKUP(P31,Workflow!$S$6:$S$270,Workflow!$W$6:$W$270)} -> P237 | T31: 45982 | U31: 6 | V31: {=XLOOKUP(T31,Workflow!$T$6:$T$270,Workflow!$W$6:$W$270)} -> P207
J32: AR | K32: 1 | M32: Internal Reason | N32: 9 | P32: 45969 | Q32: 2 | R32: {=XLOOKUP(P32,Workflow!$S$6:$S$270,Workflow!$W$6:$W$270)} -> P178 | T32: 45976 | U32: 1 | V32: {=XLOOKUP(T32,Workflow!$T$6:$T$270,Workflow!$W$6:$W$270)} -> P236
J33: BR | K33: 66 | M33: No Response | N33: 18 | P33: 45967 | Q33: 1 | R33: {=XLOOKUP(P33,Workflow!$S$6:$S$270,Workflow!$W$6:$W$270)} -> P210 | T33: 45975 | U33: 1 | V33: {=XLOOKUP(T33,Workflow!$T$6:$T$270,Workflow!$W$6:$W$270)} -> P227
J34: MDL | K34: 1 | M34: Postponed | N34: 2 | P34: 45962 | Q34: 2 | R34: {=XLOOKUP(P34,Workflow!$S$6:$S$270,Workflow!$W$6:$W$270)} -> P208 | T34: 45974 | U34: 1 | V34: {=XLOOKUP(T34,Workflow!$T$6:$T$270,Workflow!$W$6:$W$270)} -> P180
J35: MWB | K35: 17 | M35: Grand Total | N35: 264 | P35: 45961 | Q35: 3 | R35: {=XLOOKUP(P35,Workflow!$S$6:$S$270,Workflow!$W$6:$W$270)} -> P147 | T35: 45973 | U35: 2 | V35: {=XLOOKUP(T35,Workflow!$T$6:$T$270,Workflow!$W$6:$W$270)} -> P237
J36: OME | K36: 50 | P36: 45960 | Q36: 1 | R36: {=XLOOKUP(P36,Workflow!$S$6:$S$270,Workflow!$W$6:$W$270)} -> P196 | T36: 45970 | U36: 1 | V36: {=XLOOKUP(T36,Workflow!$T$6:$T$270,Workflow!$W$6:$W$270)} -> P178
J37: RA | K37: 1 | P37: 45957 | Q37: 1 | R37: {=XLOOKUP(P37,Workflow!$S$6:$S$270,Workflow!$W$6:$W$270)} -> P217 | T37: 45969 | U37: 1 | V37: {=XLOOKUP(T37,Workflow!$T$6:$T$270,Workflow!$W$6:$W$270)} -> P198
J38: SB | K38: 45 | M38: Customer Category | N38: COUNTA of Quotation Number | P38: 45955 | Q38: 1 | R38: {=XLOOKUP(P38,Workflow!$S$6:$S$270,Workflow!$W$6:$W$270)} -> P229 | T38: 45967 | U38: 1 | V38: {=XLOOKUP(T38,Workflow!$T$6:$T$270,Workflow!$W$6:$W$270)} -> P210
J39: SYS | K39: 12 | N39: 2 | P39: 45954 | Q39: 3 | R39: {=XLOOKUP(P39,Workflow!$S$6:$S$270,Workflow!$W$6:$W$270)} -> P106 | T39: 45963 | U39: 1 | V39: {=XLOOKUP(T39,Workflow!$T$6:$T$270,Workflow!$W$6:$W$270)} -> P226
J40: TF | K40: 44 | M40: Campus | N40: 4 | P40: 45953 | Q40: 1 | R40: {=XLOOKUP(P40,Workflow!$S$6:$S$270,Workflow!$W$6:$W$270)} -> P223 | T40: 45962 | U40: 3 | V40: {=XLOOKUP(T40,Workflow!$T$6:$T$270,Workflow!$W$6:$W$270)} -> P196
J41: UT | K41: 27 | M41: Corporate | N41: 200 | P41: 45952 | Q41: 1 | R41: {=XLOOKUP(P41,Workflow!$S$6:$S$270,Workflow!$W$6:$W$270)} -> P182 | T41: 45961 | U41: 2 | V41: {=XLOOKUP(T41,Workflow!$T$6:$T$270,Workflow!$W$6:$W$270)} -> P147
J42: Grand Total | K42: 264 | M42: Goverment | N42: 37 | P42: 45951 | Q42: 1 | R42: {=XLOOKUP(P42,Workflow!$S$6:$S$270,Workflow!$W$6:$W$270)} -> P126 | T42: 45958 | U42: 1 | V42: {=XLOOKUP(T42,Workflow!$T$6:$T$270,Workflow!$W$6:$W$270)} -> P217
M43: Other | N43: 17 | P43: 45948 | Q43: 2 | R43: {=XLOOKUP(P43,Workflow!$S$6:$S$270,Workflow!$W$6:$W$270)} -> P199 | T43: 45956 | U43: 1 | V43: {=XLOOKUP(T43,Workflow!$T$6:$T$270,Workflow!$W$6:$W$270)} -> P106
J44: Quotation Status | K44: COUNTA of Quotation Number | M44: Student | N44: 4 | P44: 45947 | Q44: 2 | R44: {=XLOOKUP(P44,Workflow!$S$6:$S$270,Workflow!$W$6:$W$270)} -> P200 | T44: 45955 | U44: 2 | V44: {=XLOOKUP(T44,Workflow!$T$6:$T$270,Workflow!$W$6:$W$270)} -> P214
J45: Cancel | K45: 142 | M45: Grand Total | N45: 264 | P45: 45946 | Q45: 1 | R45: {=XLOOKUP(P45,Workflow!$S$6:$S$270,Workflow!$W$6:$W$270)} -> P152 | T45: 45954 | U45: 2 | V45: {=XLOOKUP(T45,Workflow!$T$6:$T$270,Workflow!$W$6:$W$270)} -> P223
J46: Signed & Deal | K46: 122 | P46: 45941 | Q46: 2 | R46: {=XLOOKUP(P46,Workflow!$S$6:$S$270,Workflow!$W$6:$W$270)} -> P173 | T46: 45952 | U46: 1 | V46: {=XLOOKUP(T46,Workflow!$T$6:$T$270,Workflow!$W$6:$W$270)} -> P182
J47: Grand Total | K47: 264 | P47: 45940 | Q47: 1 | R47: {=XLOOKUP(P47,Workflow!$S$6:$S$270,Workflow!$W$6:$W$270)} -> P206 | T47: 45951 | U47: 1 | V47: {=XLOOKUP(T47,Workflow!$T$6:$T$270,Workflow!$W$6:$W$270)} -> P126
M48: Prog | N48: COUNTA of Quotation Number | P48: 45939 | Q48: 1 | R48: {=XLOOKUP(P48,Workflow!$S$6:$S$270,Workflow!$W$6:$W$270)} -> P209 | T48: 45948 | U48: 3 | V48: {=XLOOKUP(T48,Workflow!$T$6:$T$270,Workflow!$W$6:$W$270)} -> P200
N49: 0 | P49: 45938 | Q49: 1 | R49: {=XLOOKUP(P49,Workflow!$S$6:$S$270,Workflow!$W$6:$W$270)} -> P129 | T49: 45947 | U49: 1 | V49: {=XLOOKUP(T49,Workflow!$T$6:$T$270,Workflow!$W$6:$W$270)} -> P211
M50: Cooking Race | N50: 1 | P50: 45937 | Q50: 2 | R50: {=XLOOKUP(P50,Workflow!$S$6:$S$270,Workflow!$W$6:$W$270)} -> P191 | T50: 45946 | U50: 1 | V50: {=XLOOKUP(T50,Workflow!$T$6:$T$270,Workflow!$W$6:$W$270)} -> P152
M51: ENT | N51: 8 | P51: 45931 | Q51: 1 | R51: {=XLOOKUP(P51,Workflow!$S$6:$S$270,Workflow!$W$6:$W$270)} -> P216 | T51: 45941 | U51: 2 | V51: {=XLOOKUP(T51,Workflow!$T$6:$T$270,Workflow!$W$6:$W$270)} -> P173
M52: FG | N52: 23 | P52: 45930 | Q52: 1 | R52: {=XLOOKUP(P52,Workflow!$S$6:$S$270,Workflow!$W$6:$W$270)} -> P172 | T52: 45940 | U52: 1 | V52: {=XLOOKUP(T52,Workflow!$T$6:$T$270,Workflow!$W$6:$W$270)} -> P206
J53: Event Category | K53: COUNTA of Quotation Number | M53: Full Arrangement | N53: 46 | P53: 45928 | Q53: 1 | R53: {=XLOOKUP(P53,Workflow!$S$6:$S$270,Workflow!$W$6:$W$270)} -> P113 | T53: 45939 | U53: 3 | V53: {=XLOOKUP(T53,Workflow!$T$6:$T$270,Workflow!$W$6:$W$270)} -> P191
K54: 0 | M54: Inflatable Race | N54: 1 | P54: 45926 | Q54: 2 | R54: {=XLOOKUP(P54,Workflow!$S$6:$S$270,Workflow!$W$6:$W$270)} -> P186 | T54: 45938 | U54: 1 | V54: {=XLOOKUP(T54,Workflow!$T$6:$T$270,Workflow!$W$6:$W$270)} -> P129
J55: Employee Gathering | K55: 150 | M55: Master Chef | N55: 1 | P55: 45925 | Q55: 2 | R55: {=XLOOKUP(P55,Workflow!$S$6:$S$270,Workflow!$W$6:$W$270)} -> P181 | T55: 45931 | U55: 1 | V55: {=XLOOKUP(T55,Workflow!$T$6:$T$270,Workflow!$W$6:$W$270)} -> P216
J56: Entertainment | K56: 11 | M56: OFR | N56: 14 | P56: 45923 | Q56: 2 | R56: {=XLOOKUP(P56,Workflow!$S$6:$S$270,Workflow!$W$6:$W$270)} -> P125 | T56: 45930 | U56: 1 | V56: {=XLOOKUP(T56,Workflow!$T$6:$T$270,Workflow!$W$6:$W$270)} -> P172
J57: Family Gathering | K57: 8 | M57: Others | N57: 17 | P57: 45920 | Q57: 1 | R57: {=XLOOKUP(P57,Workflow!$S$6:$S$270,Workflow!$W$6:$W$270)} -> P203 | T57: 45928 | U57: 1 | V57: {=XLOOKUP(T57,Workflow!$T$6:$T$270,Workflow!$W$6:$W$270)} -> P113
J58: Meeting | K58: 11 | M58: Production | N58: 61 | P58: 45918 | Q58: 1 | R58: {=XLOOKUP(P58,Workflow!$S$6:$S$270,Workflow!$W$6:$W$270)} -> P118 | T58: 45927 | U58: 2 | V58: {=XLOOKUP(T58,Workflow!$T$6:$T$270,Workflow!$W$6:$W$270)} -> P181
J59: Other | K59: 26 | M59: RFT | N59: 9 | P59: 45917 | Q59: 1 | R59: {=XLOOKUP(P59,Workflow!$S$6:$S$270,Workflow!$W$6:$W$270)} -> P183 | T59: 45926 | U59: 1 | V59: {=XLOOKUP(T59,Workflow!$T$6:$T$270,Workflow!$W$6:$W$270)} -> P186
J60: Production | K60: 49 | M60: Study tour | N60: 1 | P60: 45914 | Q60: 1 | R60: {=XLOOKUP(P60,Workflow!$S$6:$S$270,Workflow!$W$6:$W$270)} -> P174 | T60: 45925 | U60: 1 | V60: {=XLOOKUP(T60,Workflow!$T$6:$T$270,Workflow!$W$6:$W$270)} -> P188
J61: Sport Event | K61: 1 | M61: TB | N61: 67 | P61: 45913 | Q61: 1 | R61: {=XLOOKUP(P61,Workflow!$S$6:$S$270,Workflow!$W$6:$W$270)} -> P190 | T61: 45923 | U61: 2 | V61: {=XLOOKUP(T61,Workflow!$T$6:$T$270,Workflow!$W$6:$W$270)} -> P125
J62: Tour | K62: 8 | M62: TB - Scavenger Hunt | N62: 6 | P62: 45912 | Q62: 2 | R62: {=XLOOKUP(P62,Workflow!$S$6:$S$270,Workflow!$W$6:$W$270)} -> P055 | T62: 45921 | U62: 1 | V62: {=XLOOKUP(T62,Workflow!$T$6:$T$270,Workflow!$W$6:$W$270)} -> P203
J63: Grand Total | K63: 264 | M63: TOG | N63: 1 | P63: 45911 | Q63: 1 | R63: {=XLOOKUP(P63,Workflow!$S$6:$S$270,Workflow!$W$6:$W$270)} -> P156 | T63: 45918 | U63: 2 | V63: {=XLOOKUP(T63,Workflow!$T$6:$T$270,Workflow!$W$6:$W$270)} -> P183
M64: Trekking | N64: 8 | P64: 45908 | Q64: 1 | R64: {=XLOOKUP(P64,Workflow!$S$6:$S$270,Workflow!$W$6:$W$270)} -> P177 | T64: 45915 | U64: 1 | V64: {=XLOOKUP(T64,Workflow!$T$6:$T$270,Workflow!$W$6:$W$270)} -> P160
M65: Grand Total | N65: 264 | P65: 45906 | Q65: 2 | R65: {=XLOOKUP(P65,Workflow!$S$6:$S$270,Workflow!$W$6:$W$270)} -> P139 | T65: 45914 | U65: 1 | V65: {=XLOOKUP(T65,Workflow!$T$6:$T$270,Workflow!$W$6:$W$270)} -> P174
P66: 45904 | Q66: 2 | R66: {=XLOOKUP(P66,Workflow!$S$6:$S$270,Workflow!$W$6:$W$270)} -> P146 | T66: 45913 | U66: 3 | V66: {=XLOOKUP(T66,Workflow!$T$6:$T$270,Workflow!$W$6:$W$270)} -> P055
P67: 45902 | Q67: 2 | R67: {=XLOOKUP(P67,Workflow!$S$6:$S$270,Workflow!$W$6:$W$270)} -> P150 | T67: 45911 | U67: 1 | V67: {=XLOOKUP(T67,Workflow!$T$6:$T$270,Workflow!$W$6:$W$270)} -> P156
J68: Program Status | K68: COUNTA of Program Status | L68: SUM of Budget (Rp) | M68: COUNTA of PM | P68: 45901 | Q68: 3 | R68: {=XLOOKUP(P68,Workflow!$S$6:$S$270,Workflow!$W$6:$W$270)} -> P114 | T68: 45909 | U68: 1 | V68: {=XLOOKUP(T68,Workflow!$T$6:$T$270,Workflow!$W$6:$W$270)} -> P177
J69: Cancel | K69: 142 | L69: 20942116661 | M69: 142 | P69: 45899 | Q69: 1 | R69: {=XLOOKUP(P69,Workflow!$S$6:$S$270,Workflow!$W$6:$W$270)} -> P136 | T69: 45907 | U69: 1 | V69: {=XLOOKUP(T69,Workflow!$T$6:$T$270,Workflow!$W$6:$W$270)} -> P162
J70: Confirm | K70: 122 | L70: 10573503222 | M70: 122 | P70: 45898 | Q70: 3 | R70: {=XLOOKUP(P70,Workflow!$S$6:$S$270,Workflow!$W$6:$W$270)} -> P112 | T70: 45906 | U70: 2 | V70: {=XLOOKUP(T70,Workflow!$T$6:$T$270,Workflow!$W$6:$W$270)} -> P139
J71: Grand Total | K71: 264 | L71: 31515619883 | M71: 264 | P71: 45896 | Q71: 1 | R71: {=XLOOKUP(P71,Workflow!$S$6:$S$270,Workflow!$W$6:$W$270)} -> P128 | T71: 45904 | U71: 1 | V71: {=XLOOKUP(T71,Workflow!$T$6:$T$270,Workflow!$W$6:$W$270)} -> P146
P72: 45895 | Q72: 1 | R72: {=XLOOKUP(P72,Workflow!$S$6:$S$270,Workflow!$W$6:$W$270)} -> P158 | T72: 45903 | U72: 1 | V72: {=XLOOKUP(T72,Workflow!$T$6:$T$270,Workflow!$W$6:$W$270)} -> P195
P73: 45894 | Q73: 1 | R73: {=XLOOKUP(P73,Workflow!$S$6:$S$270,Workflow!$W$6:$W$270)} -> P194 | T73: 45902 | U73: 2 | V73: {=XLOOKUP(T73,Workflow!$T$6:$T$270,Workflow!$W$6:$W$270)} -> P133
P74: 45890 | Q74: 1 | R74: {=XLOOKUP(P74,Workflow!$S$6:$S$270,Workflow!$W$6:$W$270)} -> P171 | T74: 45901 | U74: 2 | V74: {=XLOOKUP(T74,Workflow!$T$6:$T$270,Workflow!$W$6:$W$270)} -> P114
P75: 45889 | Q75: 2 | R75: {=XLOOKUP(P75,Workflow!$S$6:$S$270,Workflow!$W$6:$W$270)} -> P124 | T75: 45899 | U75: 2 | V75: {=XLOOKUP(T75,Workflow!$T$6:$T$270,Workflow!$W$6:$W$270)} -> P142
P76: 45888 | Q76: 2 | R76: {=XLOOKUP(P76,Workflow!$S$6:$S$270,Workflow!$W$6:$W$270)} -> P193 | T76: 45898 | U76: 2 | V76: {=XLOOKUP(T76,Workflow!$T$6:$T$270,Workflow!$W$6:$W$270)} -> P112
P77: 45886 | Q77: 2 | R77: {=XLOOKUP(P77,Workflow!$S$6:$S$270,Workflow!$W$6:$W$270)} -> P100 | T77: 45896 | U77: 1 | V77: {=XLOOKUP(T77,Workflow!$T$6:$T$270,Workflow!$W$6:$W$270)} -> P128
K78: Program Status | L78: Values | P78: 45885 | Q78: 2 | R78: {=XLOOKUP(P78,Workflow!$S$6:$S$270,Workflow!$W$6:$W$270)} -> P110 | T78: 45895 | U78: 2 | V78: {=XLOOKUP(T78,Workflow!$T$6:$T$270,Workflow!$W$6:$W$270)} -> P194
K79: Confirm | M79: Grand Total | P79: 45884 | Q79: 2 | R79: {=XLOOKUP(P79,Workflow!$S$6:$S$270,Workflow!$W$6:$W$270)} -> P120 | T79: 45891 | U79: 1 | V79: {=XLOOKUP(T79,Workflow!$T$6:$T$270,Workflow!$W$6:$W$270)} -> P171
F80: 0.15 | G80: 15000000000 | J80: PO | K80: SUM of Budget (Rp) | L80: SUM of QTY | M80: SUM of Budget (Rp) | N80: SUM of QTY | P80: 45880 | Q80: 2 | R80: {=XLOOKUP(P80,Workflow!$S$6:$S$270,Workflow!$W$6:$W$270)} -> P167 | T80: 45890 | U80: 1 | V80: {=XLOOKUP(T80,Workflow!$T$6:$T$270,Workflow!$W$6:$W$270)} -> P166
E81: AR | F81: =K81/K91*100% -> 0.11741775 | G81: =F81*$G$80 -> 1761266320 | H81: 1200000000 | I81: =H81/$H$93*100% -> 0.078947368 | J81: AR | K81: 1241517007 | L81: 74 | M81: 1241517007 | N81: 74 | P81: 45879 | Q81: 2 | R81: {=XLOOKUP(P81,Workflow!$S$6:$S$270,Workflow!$W$6:$W$270)} -> P059 | T81: 45889 | U81: 3 | V81: {=XLOOKUP(T81,Workflow!$T$6:$T$270,Workflow!$W$6:$W$270)} -> P193
E82: BR | F82: =K82/K91*100% -> 0.095170182 | G82: =F82*$G$80 -> 1427552737 | H82: 1800000000 | I82: =H82/$H$93*100% -> 0.11842105 | J82: BR | K82: 1006282231 | L82: 870 | M82: 1006282231 | N82: 870 | P82: 45878 | Q82: 3 | R82: {=XLOOKUP(P82,Workflow!$S$6:$S$270,Workflow!$W$6:$W$270)} -> P115 | T82: 45886 | U82: 3 | V82: {=XLOOKUP(T82,Workflow!$T$6:$T$270,Workflow!$W$6:$W$270)} -> P120
E83: JIP | F83: =K84/K91*100% -> 0.59241319 | G83: =F83*$G$80 -> 8886197914 | H83: 5500000000 | I83: =H83/$H$93*100% -> 0.36184211 | J83: JC | K83: 226594000 | L83: 70 | M83: 226594000 | N83: 70 | P83: 45877 | Q83: 2 | R83: {=XLOOKUP(P83,Workflow!$S$6:$S$270,Workflow!$W$6:$W$270)} -> P047 | T83: 45885 | U83: 2 | V83: {=XLOOKUP(T83,Workflow!$T$6:$T$270,Workflow!$W$6:$W$270)} -> P110
E84: MWB | F84: =K85/K91*100% -> 0.0049638231 | G84: =F84*$G$80 -> 74457347 | H84: 1200000000 | I84: =H84/$H$93*100% -> 0.078947368 | J84: JIP | K84: 6263882818 | L84: 7308 | M84: 6263882818 | N84: 7308 | P84: 45876 | Q84: 1 | R84: {=XLOOKUP(P84,Workflow!$S$6:$S$270,Workflow!$W$6:$W$270)} -> P153 | T84: 45884 | U84: 1 | V84: {=XLOOKUP(T84,Workflow!$T$6:$T$270,Workflow!$W$6:$W$270)} -> P131
E85: OME | G85: =F85*$G$80 -> 0 | H85: 500000000 | I85: =H85/$H$93*100% -> 0.032894737 | J85: MWB | K85: 52485000 | L85: 55 | M85: 52485000 | N85: 55 | P85: 45875 | Q85: 2 | R85: {=XLOOKUP(P85,Workflow!$S$6:$S$270,Workflow!$W$6:$W$270)} -> P138 | T85: 45881 | U85: 1 | V85: {=XLOOKUP(T85,Workflow!$T$6:$T$270,Workflow!$W$6:$W$270)} -> P167
E86: RA | F86: =K86/K91*100% -> 0.0035087709 | G86: =F86*$G$80 -> 52631563 | H86: 1000000000 | I86: =H86/$H$93*100% -> 0.065789474 | J86: RA | K86: 37100000 | L86: 91 | M86: 37100000 | N86: 91 | P86: 45872 | Q86: 1 | R86: {=XLOOKUP(P86,Workflow!$S$6:$S$270,Workflow!$W$6:$W$270)} -> P144 | T86: 45880 | U86: 1 | V86: {=XLOOKUP(T86,Workflow!$T$6:$T$270,Workflow!$W$6:$W$270)} -> P165
E87: SBK | F87: =K87/K91*100% -> 0.067451569 | G87: =F87*$G$80 -> 1011773532 | H87: 1000000000 | I87: =H87/$H$93*100% -> 0.065789474 | J87: SBK | K87: 713199380 | L87: 1003 | M87: 713199380 | N87: 1003 | P87: 45871 | Q87: 1 | R87: {=XLOOKUP(P87,Workflow!$S$6:$S$270,Workflow!$W$6:$W$270)} -> P148 | T87: 45879 | U87: 3 | V87: {=XLOOKUP(T87,Workflow!$T$6:$T$270,Workflow!$W$6:$W$270)} -> P047
E88: SR | F88: =K88/K91*100% -> 0.060527457 | G88: =F88*$G$80 -> 9.0791185e+08 | H88: 800000000 | I88: =H88/$H$93*100% -> 0.052631579 | J88: SR | K88: 639987261 | L88: 147 | M88: 639987261 | N88: 147 | P88: 45870 | Q88: 3 | R88: {=XLOOKUP(P88,Workflow!$S$6:$S$270,Workflow!$W$6:$W$270)} -> P132 | T88: 45878 | U88: 3 | V88: {=XLOOKUP(T88,Workflow!$T$6:$T$270,Workflow!$W$6:$W$270)} -> P107
E89: SYS | F89: =K89/K91*100% -> 0.011603498 | G89: =F89*$G$80 -> 174052465 | H89: 1000000000 | I89: =H89/$H$93*100% -> 0.065789474 | J89: SYS | K89: 122689620 | L89: 1130 | M89: 122689620 | N89: 1130 | P89: 45864 | Q89: 1 | R89: {=XLOOKUP(P89,Workflow!$S$6:$S$270,Workflow!$W$6:$W$270)} -> P137 | T89: 45877 | U89: 1 | V89: {=XLOOKUP(T89,Workflow!$T$6:$T$270,Workflow!$W$6:$W$270)} -> P115
E90: TF | F90: =K90/K91*100% -> 0.025513389 | G90: =F90*$G$80 -> 382700841 | H90: 500000000 | I90: =H90/$H$93*100% -> 0.032894737 | J90: TF | K90: 269765905 | L90: 82 | M90: 269765905 | N90: 82 | P90: 45863 | Q90: 1 | R90: {=XLOOKUP(P90,Workflow!$S$6:$S$270,Workflow!$W$6:$W$270)} -> P131 | T90: 45876 | U90: 1 | V90: {=XLOOKUP(T90,Workflow!$T$6:$T$270,Workflow!$W$6:$W$270)} -> P153
E91: UT | G91: =X24+F91 -> 500000000 | H91: 500000000 | I91: =H91/$H$93*100% -> 0.032894737 | J91: Grand Total | K91: 10573503222 | L91: 10830 | M91: 10573503222 | N91: 10830 | P91: 45861 | Q91: 1 | R91: {=XLOOKUP(P91,Workflow!$S$6:$S$270,Workflow!$W$6:$W$270)} -> P143 | T91: 45875 | U91: 2 | V91: {=XLOOKUP(T91,Workflow!$T$6:$T$270,Workflow!$W$6:$W$270)} -> P138
E92: JHD | H92: 200000000 | I92: =H92/$H$93*100% -> 0.013157895 | P92: 45856 | Q92: 2 | R92: {=XLOOKUP(P92,Workflow!$S$6:$S$270,Workflow!$W$6:$W$270)} -> P105 | T92: 45872 | U92: 1 | V92: {=XLOOKUP(T92,Workflow!$T$6:$T$270,Workflow!$W$6:$W$270)} -> P144
G93: =sum(G81:G91) -> 15178544572 | H93: =sum(H81:H92) -> 15200000000 | P93: 45855 | Q93: 4 | R93: {=XLOOKUP(P93,Workflow!$S$6:$S$270,Workflow!$W$6:$W$270)} -> P052 | T93: 45871 | U93: 4 | V93: {=XLOOKUP(T93,Workflow!$T$6:$T$270,Workflow!$W$6:$W$270)} -> P132
J94: PM | K94: Program Status | L94: COUNTA of Program Status | M94: COUNTA of Program Status | P94: 45853 | Q94: 1 | R94: {=XLOOKUP(P94,Workflow!$S$6:$S$270,Workflow!$W$6:$W$270)} -> P123 | T94: 45870 | U94: 1 | V94: {=XLOOKUP(T94,Workflow!$T$6:$T$270,Workflow!$W$6:$W$270)} -> P141
L95: 0 | M95: 0 | P95: 45850 | Q95: 2 | R95: {=XLOOKUP(P95,Workflow!$S$6:$S$270,Workflow!$W$6:$W$270)} -> P102 | T95: 45864 | U95: 1 | V95: {=XLOOKUP(T95,Workflow!$T$6:$T$270,Workflow!$W$6:$W$270)} -> P137
J96: Total | L96: 0 | M96: 0 | P96: 45848 | Q96: 1 | R96: {=XLOOKUP(P96,Workflow!$S$6:$S$270,Workflow!$W$6:$W$270)} -> P202 | T96: 45861 | U96: 1 | V96: {=XLOOKUP(T96,Workflow!$T$6:$T$270,Workflow!$W$6:$W$270)} -> P143
J97: AR Total | L97: 1 | M97: 1 | P97: 45847 | Q97: 2 | R97: {=XLOOKUP(P97,Workflow!$S$6:$S$270,Workflow!$W$6:$W$270)} -> P122 | T97: 45857 | U97: 4 | V97: {=XLOOKUP(T97,Workflow!$T$6:$T$270,Workflow!$W$6:$W$270)} -> P052
J98: BR | K98: Cancel | L98: 34 | M98: 34 | P98: 45842 | Q98: 1 | R98: {=XLOOKUP(P98,Workflow!$S$6:$S$270,Workflow!$W$6:$W$270)} -> P135 | T98: 45856 | U98: 1 | V98: {=XLOOKUP(T98,Workflow!$T$6:$T$270,Workflow!$W$6:$W$270)} -> P105
K99: Confirm | L99: 32 | M99: 32 | P99: 45840 | Q99: 1 | R99: {=XLOOKUP(P99,Workflow!$S$6:$S$270,Workflow!$W$6:$W$270)} -> P133 | T99: 45855 | U99: 1 | V99: {=XLOOKUP(T99,Workflow!$T$6:$T$270,Workflow!$W$6:$W$270)} -> P117
J100: BR Total | L100: 66 | M100: 66 | P100: 45835 | Q100: 1 | R100: {=XLOOKUP(P100,Workflow!$S$6:$S$270,Workflow!$W$6:$W$270)} -> P101 | T100: 45853 | U100: 1 | V100: {=XLOOKUP(T100,Workflow!$T$6:$T$270,Workflow!$W$6:$W$270)} -> P123
...
